[{"app_id": "com.endlessm.video_kids", "date_created": 1636553918.0, "description": "Mostly videos, some of them are not so educational.", "distro": "Endless", "karma_down": 1, "karma_up": 2, "locale": "en_US.UTF-8", "rating": 80, "reported": 0, "review_id": 436906, "score": 0, "summary": "Its OK", "user_display": "Byron", "version": "eos3"}, {"app_id": "com.endlessm.video_kids", "date_created": 1699535949.0, "description": "RADICLE\nAMAZING", "distro": "Endless", "karma_down": 0, "karma_up": 0, "locale": "en_US.utf8", "rating": 100, "reported": 0, "review_id": 606249, "score": 0, "summary": "THATS SO COOL DUDE", "user_display": "Shared Account", "version": "eos3"}, {"app_id": "com.endlessm.video_kids", "date_created": 1678280766.0, "description": "h\u00e4jsdljogfVIOUGfWGFOOOOOGIOgWOTO9G H\u00e4sslicvh", "distro": "Endless", "karma_down": 0, "karma_up": 0, "locale": "de_DE.UTF-8", "rating": 20, "reported": 0, "review_id": 571008, "score": 0, "summary": "Scwei\u00dfe", "user_display": "UwU.Nja.Ichi.Nisa.Nja.Arigato.", "version": "eos3"}]