[{"app_id": "com.amazon.Workspaces", "date_created": 1606637352.0, "description": "Slow and buggy solution", "distro": "Fedora", "karma_down": 0, "karma_up": 0, "locale": "en_US.UTF-8", "rating": 20, "reported": 0, "review_id": 310131, "score": 0, "summary": "Slow and buggy", "user_display": null, "version": "3.1.0.813"}, {"app_id": "com.amazon.Workspaces", "date_created": 1606688893.0, "description": "Convenient packaging for AWS WorkSpace client. Previously I had a podman container building from Ubuntu for this.", "distro": "Fedora", "karma_down": 0, "karma_up": 0, "locale": "en_AU.UTF-8", "rating": 80, "reported": 0, "review_id": 310487, "score": 0, "summary": "Convenient packaging for AWS WorkSpace client", "user_display": "Richard Green", "version": "3.1.0.813"}, {"app_id": "com.amazon.Workspaces", "date_created": 1615149780.0, "description": "Any attempt to install latest version (meaning March 2021) ends on a 403:Forbidden error when attempting to download the source package from AWS Cloudfront\n\nProbably the download code needs some tweaking", "distro": "Fedora", "karma_down": 0, "karma_up": 0, "locale": "en_GB.UTF-8", "rating": 60, "reported": 0, "review_id": 349505, "score": 0, "summary": "Convenient but in the last 4-5 days the download fails", "user_display": "Emanuel Corra'", "version": "3.1.0.813"}, {"app_id": "com.amazon.Workspaces", "date_created": 1623868874.0, "description": "I don't trust amazon", "distro": "Fedora", "karma_down": 0, "karma_up": 0, "locale": "en_GB.UTF-8", "rating": 20, "reported": 0, "review_id": 389404, "score": 0, "summary": "don't approve", "user_display": "david", "version": "3.1.8.1198"}, {"app_id": "com.amazon.Workspaces", "date_created": 1627356080.0, "description": "Finally no worries about converting ubuntu debs via alien. This works great!", "distro": "Fedora", "karma_down": 0, "karma_up": 0, "locale": "en_US.UTF-8", "rating": 100, "reported": 0, "review_id": 403169, "score": 0, "summary": "Runs great on Fedora 34", "user_display": "Fatih", "version": "3.1.9.1245"}, {"app_id": "com.amazon.Workspaces", "date_created": 1629285116.0, "description": "the app works (almost) flawlessly", "distro": "Ubuntu", "karma_down": 0, "karma_up": 0, "locale": "en_US.UTF-8", "rating": 80, "reported": 0, "review_id": 410721, "score": 0, "summary": "it works", "user_display": "mint", "version": "4.0.1.1302"}, {"app_id": "com.amazon.Workspaces", "date_created": 1652824791.0, "description": "Funciona perfectamente y hace todo lo que tiene que hacer. Muchas gracias", "distro": "Ubuntu", "karma_down": 0, "karma_up": 0, "locale": "es_CO.UTF-8", "rating": 100, "reported": 0, "review_id": 487701, "score": 0, "summary": "Funciona perfectamente", "user_display": "Leonardo", "version": "4.1.0.1523"}]