[{"app_id": "io.github.giantpinkrobots.varia", "date_created": 1717156928.0, "description": "The software keeps crashing frequently and removes downloads from history, making it impossible to track or resume them. The instability and data loss are incredibly frustrating. Avoid this download manager if you value your time and sanity.", "distro": "Fedora Linux", "karma_down": 0, "karma_up": 0, "locale": "en_US.UTF-8", "rating": 20, "reported": 0, "review_id": 623798, "score": 14, "summary": "so bad", "user_display": "M", "version": "v2024.5.7"}, {"app_id": "io.github.giantpinkrobots.varia", "date_created": 1701917662.0, "description": "It is a nice app!", "distro": "Fedora Linux", "karma_down": 1, "karma_up": 3, "locale": "en_US.UTF-8", "rating": 100, "reported": 0, "review_id": 608635, "score": 10, "summary": "Nice!", "user_display": "Ariel Ch", "version": "v2023.12.7"}, {"app_id": "io.github.giantpinkrobots.varia", "date_created": 1702269114.0, "description": "Looking forward to more updates and advanced settings!", "distro": "Fedora Linux", "karma_down": 0, "karma_up": 0, "locale": "en_US.UTF-8", "rating": 100, "reported": 0, "review_id": 608996, "score": 0, "summary": "Perfect", "user_display": "Mohammad", "version": "v2023.12.8"}]