[{"app_id": "io.snapcraft.buzz-RSpCVxCNDwoTXHPXhlYQnziD0jQhVnKA", "date_created": 1710869719.0, "description": "Si funciona, que creo que si, me ayudar\u00e1", "distro": "Ubuntu", "karma_down": 0, "karma_up": 0, "locale": "es_ES.UTF-8", "rating": 100, "reported": 0, "review_id": 617715, "score": 0, "summary": "Parece sencillo", "user_display": "carlos", "version": "0"}, {"app_id": "io.snapcraft.buzz-RSpCVxCNDwoTXHPXhlYQnziD0jQhVnKA", "date_created": 1704890656.0, "description": "under Ubuntu 22.04.3 LTS", "distro": "Ubuntu", "karma_down": 0, "karma_up": 0, "locale": "fr_FR.UTF-8", "rating": 20, "reported": 0, "review_id": 611559, "score": 0, "summary": "Does not run", "user_display": "GSu", "version": "0"}]