[{"app_id": "io.snapcraft.pycharm-professional-Uqpw0ZWqy6Wh4mgaWE0rxgM5tAGCwf4D", "date_created": 1556160917.0, "description": "This is program is perfect for python calculaton, but I just don't understand why when I try to search for the anaconda, the PhCharm pro go up instead. It is because ubuntu software center not have anaconda yet?\nor just want us to install some kind of alternative????\nI don't want ubuntu to biasely select resources.", "distro": "Ubuntu", "karma_down": 5, "karma_up": 8, "locale": "en_US", "rating": 100, "reported": 0, "review_id": 24983, "score": 0, "summary": "I just downloaded this program", "user_display": "light", "version": "2019.1.1"}, {"app_id": "io.snapcraft.pycharm-professional-Uqpw0ZWqy6Wh4mgaWE0rxgM5tAGCwf4D", "date_created": 1556262896.0, "description": "Best IDE for Python", "distro": "Ubuntu", "karma_down": 3, "karma_up": 7, "locale": "en_IN", "rating": 100, "reported": 0, "review_id": 25550, "score": 0, "summary": "Best IDE for Python", "user_display": "Bataman", "version": "2019.1.1"}, {"app_id": "io.snapcraft.pycharm-professional-Uqpw0ZWqy6Wh4mgaWE0rxgM5tAGCwf4D", "date_created": 1557222915.0, "description": "good ide, i love it.", "distro": "Ubuntu", "karma_down": 1, "karma_up": 2, "locale": "en_US", "rating": 100, "reported": 0, "review_id": 30458, "score": 0, "summary": "Great app, its so good", "user_display": "dev", "version": "2019.1.1"}, {"app_id": "io.snapcraft.pycharm-professional-Uqpw0ZWqy6Wh4mgaWE0rxgM5tAGCwf4D", "date_created": 1558647825.0, "description": "Great tool for working with Python.", "distro": "Ubuntu", "karma_down": 1, "karma_up": 4, "locale": "en_US", "rating": 100, "reported": 0, "review_id": 37388, "score": 0, "summary": "Very useful", "user_display": "Valery", "version": "2019.1.2"}, {"app_id": "io.snapcraft.pycharm-professional-Uqpw0ZWqy6Wh4mgaWE0rxgM5tAGCwf4D", "date_created": 1559076913.0, "description": "this is program good and bad !\nfor what? \n1 - Too Large Size of Program [ :( ]\n2 - Powerfully IDE", "distro": "Ubuntu", "karma_down": 4, "karma_up": 4, "locale": "en_US", "rating": 100, "reported": 0, "review_id": 39674, "score": 0, "summary": "good and bad", "user_display": "hesam", "version": "2019.1.2"}, {"app_id": "io.snapcraft.pycharm-professional-Uqpw0ZWqy6Wh4mgaWE0rxgM5tAGCwf4D", "date_created": 1559283294.0, "description": "powerful\nit's perfect", "distro": "Ubuntu", "karma_down": 1, "karma_up": 1, "locale": "en_NZ", "rating": 80, "reported": 0, "review_id": 40811, "score": 0, "summary": "Has it's downsides, but very good", "user_display": "Bevan", "version": "2019.1.3"}, {"app_id": "io.snapcraft.pycharm-professional-Uqpw0ZWqy6Wh4mgaWE0rxgM5tAGCwf4D", "date_created": 1561736516.0, "description": "Jet Brains know how to make a great IDE, I use Jet Brains' on every programming language.", "distro": "Ubuntu", "karma_down": 0, "karma_up": 0, "locale": "en_US", "rating": 100, "reported": 0, "review_id": 53370, "score": 0, "summary": "If you're Python programmer you have to get it", "user_display": "Charles", "version": "2019.1.3"}, {"app_id": "io.snapcraft.pycharm-professional-Uqpw0ZWqy6Wh4mgaWE0rxgM5tAGCwf4D", "date_created": 1561905247.0, "description": "i think this is a best ide for python developing", "distro": "Ubuntu", "karma_down": 0, "karma_up": 0, "locale": "en_US", "rating": 100, "reported": 0, "review_id": 54078, "score": 0, "summary": "Great For Python", "user_display": "Anas Al Zuvix", "version": "2019.1.3"}, {"app_id": "io.snapcraft.pycharm-professional-Uqpw0ZWqy6Wh4mgaWE0rxgM5tAGCwf4D", "date_created": 1562449032.0, "description": "Not only this but all tools from Jetbrains are perfect.", "distro": "Ubuntu", "karma_down": 0, "karma_up": 0, "locale": "en_US", "rating": 100, "reported": 0, "review_id": 56604, "score": 0, "summary": "Best IDE ever", "user_display": "l50", "version": "2019.1.3"}, {"app_id": "io.snapcraft.pycharm-professional-Uqpw0ZWqy6Wh4mgaWE0rxgM5tAGCwf4D", "date_created": 1563453718.0, "description": "I'm using it for a couple of years now and it fulfills all my developer needs.", "distro": "Ubuntu", "karma_down": 0, "karma_up": 0, "locale": "en_US", "rating": 100, "reported": 0, "review_id": 61539, "score": 0, "summary": "very good software", "user_display": "lps", "version": "2019.1.3"}, {"app_id": "io.snapcraft.pycharm-professional-Uqpw0ZWqy6Wh4mgaWE0rxgM5tAGCwf4D", "date_created": 1563561816.0, "description": "like it sdafassdf sadf sadf", "distro": "Ubuntu", "karma_down": 0, "karma_up": 0, "locale": "en_US", "rating": 100, "reported": 0, "review_id": 62088, "score": 0, "summary": "like it", "user_display": "yeneek", "version": "2019.1.3"}, {"app_id": "io.snapcraft.pycharm-professional-Uqpw0ZWqy6Wh4mgaWE0rxgM5tAGCwf4D", "date_created": 1563807470.0, "description": "I'm using this on VirtualBox and it takes about a minute to load! It's still a great application, would recommend to anyone who wants to use advanced software!", "distro": "Ubuntu", "karma_down": 0, "karma_up": 0, "locale": "en_GB", "rating": 60, "reported": 0, "review_id": 62979, "score": 0, "summary": "Bit slow, still good", "user_display": "Stephen", "version": "2019.1.3"}, {"app_id": "io.snapcraft.pycharm-professional-Uqpw0ZWqy6Wh4mgaWE0rxgM5tAGCwf4D", "date_created": 1565019288.0, "description": "Hard to install in China, poor mood", "distro": "Ubuntu", "karma_down": 0, "karma_up": 0, "locale": "en_US", "rating": 40, "reported": 0, "review_id": 68473, "score": 0, "summary": "poor app", "user_display": "linux", "version": "2019.2"}, {"app_id": "io.snapcraft.pycharm-professional-Uqpw0ZWqy6Wh4mgaWE0rxgM5tAGCwf4D", "date_created": 1565192207.0, "description": "The best IDE for Python, and most likely I don't even know about half of the awesome features it has.", "distro": "Ubuntu", "karma_down": 0, "karma_up": 0, "locale": "en_US", "rating": 100, "reported": 0, "review_id": 69250, "score": 0, "summary": "the best", "user_display": "natalia", "version": "2019.2"}, {"app_id": "io.snapcraft.pycharm-professional-Uqpw0ZWqy6Wh4mgaWE0rxgM5tAGCwf4D", "date_created": 1566236239.0, "description": "Love it!!!!!!!!", "distro": "Ubuntu", "karma_down": 0, "karma_up": 0, "locale": "en_US", "rating": 100, "reported": 0, "review_id": 74020, "score": 0, "summary": "Best IDE for Python", "user_display": "Lica-PC", "version": "2019.2"}, {"app_id": "io.snapcraft.pycharm-professional-Uqpw0ZWqy6Wh4mgaWE0rxgM5tAGCwf4D", "date_created": 1566283657.0, "description": "Very easy to optimize your workflow", "distro": "Ubuntu", "karma_down": 0, "karma_up": 0, "locale": "en_US", "rating": 100, "reported": 0, "review_id": 74209, "score": 0, "summary": "Contains everything you need", "user_display": "jan-hendrik", "version": "2019.2"}, {"app_id": "io.snapcraft.pycharm-professional-Uqpw0ZWqy6Wh4mgaWE0rxgM5tAGCwf4D", "date_created": 1566456470.0, "description": "has anyone got its license for free??", "distro": "Ubuntu", "karma_down": 0, "karma_up": 0, "locale": "en_IN", "rating": 80, "reported": 0, "review_id": 75010, "score": 0, "summary": "license key", "user_display": "Vimal Pillai", "version": "2019.2"}, {"app_id": "io.snapcraft.pycharm-professional-Uqpw0ZWqy6Wh4mgaWE0rxgM5tAGCwf4D", "date_created": 1567681881.0, "description": "because is a popular IDE \u2013 Integrated Development Environment used for programming", "distro": "Ubuntu", "karma_down": 0, "karma_up": 0, "locale": "en_US", "rating": 100, "reported": 0, "review_id": 80479, "score": 0, "summary": "Professional version recommended !!", "user_display": "Ashk", "version": "2019.2.1"}, {"app_id": "io.snapcraft.pycharm-professional-Uqpw0ZWqy6Wh4mgaWE0rxgM5tAGCwf4D", "date_created": 1567931345.0, "description": "Every day i use it and i think it best IDE that i touched", "distro": "Ubuntu", "karma_down": 0, "karma_up": 0, "locale": "en_US", "rating": 100, "reported": 0, "review_id": 81628, "score": 0, "summary": "Every day i use it", "user_display": "anduser", "version": "2019.2.1"}, {"app_id": "io.snapcraft.pycharm-professional-Uqpw0ZWqy6Wh4mgaWE0rxgM5tAGCwf4D", "date_created": 1568512499.0, "description": "It is the main app to develop Django projects", "distro": "Ubuntu", "karma_down": 0, "karma_up": 0, "locale": "en_US", "rating": 100, "reported": 0, "review_id": 84286, "score": 0, "summary": "just fine app", "user_display": "soyuz", "version": "2019.2.2"}, {"app_id": "io.snapcraft.pycharm-professional-Uqpw0ZWqy6Wh4mgaWE0rxgM5tAGCwf4D", "date_created": 1568824508.0, "description": "free access\nhigh performance", "distro": "elementary OS", "karma_down": 0, "karma_up": 0, "locale": "en_US", "rating": 100, "reported": 0, "review_id": 85740, "score": 0, "summary": "Great App in python Development", "user_display": "Hacker", "version": "2019.2.2"}, {"app_id": "io.snapcraft.pycharm-professional-Uqpw0ZWqy6Wh4mgaWE0rxgM5tAGCwf4D", "date_created": 1568907093.0, "description": "best ..........", "distro": "Fedora", "karma_down": 0, "karma_up": 0, "locale": "en_US", "rating": 100, "reported": 0, "review_id": 86091, "score": 0, "summary": "best", "user_display": "Mostafa", "version": "2019.2.2"}, {"app_id": "io.snapcraft.pycharm-professional-Uqpw0ZWqy6Wh4mgaWE0rxgM5tAGCwf4D", "date_created": 1570007848.0, "description": "best python ide", "distro": "Ubuntu", "karma_down": 0, "karma_up": 0, "locale": "en_US", "rating": 100, "reported": 0, "review_id": 91188, "score": 0, "summary": "best python ide", "user_display": "yura", "version": "2019.2.3"}, {"app_id": "io.snapcraft.pycharm-professional-Uqpw0ZWqy6Wh4mgaWE0rxgM5tAGCwf4D", "date_created": 1573441936.0, "description": "so happy using this app", "distro": "Ubuntu", "karma_down": 0, "karma_up": 0, "locale": "en_US", "rating": 100, "reported": 0, "review_id": 108876, "score": 0, "summary": "user friendly", "user_display": "Sayeed", "version": "2019.2.4"}, {"app_id": "io.snapcraft.pycharm-professional-Uqpw0ZWqy6Wh4mgaWE0rxgM5tAGCwf4D", "date_created": 1573743031.0, "description": "Pycharm is a really powerful IDE for python developing stuff", "distro": "Ubuntu", "karma_down": 0, "karma_up": 0, "locale": "en_US", "rating": 100, "reported": 0, "review_id": 110502, "score": 0, "summary": "Good app, recommened!", "user_display": "Garfield", "version": "2019.2.4"}, {"app_id": "io.snapcraft.pycharm-professional-Uqpw0ZWqy6Wh4mgaWE0rxgM5tAGCwf4D", "date_created": 1574118897.0, "description": "Best Python IDE", "distro": "Ubuntu", "karma_down": 0, "karma_up": 0, "locale": "en_US", "rating": 100, "reported": 0, "review_id": 112380, "score": 0, "summary": "mck", "user_display": "mlorenc", "version": "2019.2.4"}, {"app_id": "io.snapcraft.pycharm-professional-Uqpw0ZWqy6Wh4mgaWE0rxgM5tAGCwf4D", "date_created": 1575349349.0, "description": "Oops I didn't read the description. The program works good but I am not renting software. Charge for a license if you want money, I would pay to use it but I am not paying by the month that costs too much.", "distro": "Ubuntu", "karma_down": 0, "karma_up": 0, "locale": "en_US", "rating": 80, "reported": 0, "review_id": 118629, "score": 0, "summary": "I should have read", "user_display": "Russell Deible", "version": "2019.3"}, {"app_id": "io.snapcraft.pycharm-professional-Uqpw0ZWqy6Wh4mgaWE0rxgM5tAGCwf4D", "date_created": 1575525079.0, "description": "Great app. But after 2019.3 update (from 2019.2), when I use it on my Ubuntu 19.10 - it freezes and crashes. Pro app version! Have you got some ideas about it?", "distro": "Ubuntu", "karma_down": 0, "karma_up": 0, "locale": "en_US", "rating": 80, "reported": 0, "review_id": 119631, "score": 0, "summary": "2019.3 version freezes", "user_display": "livestreamx", "version": "2019.3"}, {"app_id": "io.snapcraft.pycharm-professional-Uqpw0ZWqy6Wh4mgaWE0rxgM5tAGCwf4D", "date_created": 1575610423.0, "description": "why icfix can not use in newest version", "distro": "Ubuntu", "karma_down": 0, "karma_up": 0, "locale": "en_US", "rating": 60, "reported": 0, "review_id": 120102, "score": 0, "summary": "bad", "user_display": "image", "version": "2019.3"}, {"app_id": "io.snapcraft.pycharm-professional-Uqpw0ZWqy6Wh4mgaWE0rxgM5tAGCwf4D", "date_created": 1576433869.0, "description": "Great range of tools for any Python project, I mainly do web dev with Django.\nSimply no other choice for me", "distro": "Ubuntu", "karma_down": 0, "karma_up": 0, "locale": "en_GB", "rating": 100, "reported": 0, "review_id": 124071, "score": 0, "summary": "Great IDE for Python", "user_display": "Connor Cordell", "version": "2019.3"}, {"app_id": "io.snapcraft.pycharm-professional-Uqpw0ZWqy6Wh4mgaWE0rxgM5tAGCwf4D", "date_created": 1577788133.0, "description": "GOOD!!!!!!!!!!!!!!", "distro": "Ubuntu", "karma_down": 0, "karma_up": 0, "locale": "en_US", "rating": 100, "reported": 0, "review_id": 130602, "score": 0, "summary": "good", "user_display": "cxx", "version": "2019.3.1"}, {"app_id": "io.snapcraft.pycharm-professional-Uqpw0ZWqy6Wh4mgaWE0rxgM5tAGCwf4D", "date_created": 1577813414.0, "description": "\u0986\u09ae\u09be\u09b0 \u09aa\u099b\u09a8\u09cd\u09a6\u09c7\u09b0 IDE", "distro": "Ubuntu", "karma_down": 0, "karma_up": 0, "locale": "en_US", "rating": 100, "reported": 0, "review_id": 130755, "score": 0, "summary": "\u09ac\u09be\u0999\u09be\u09b2\u09bf \u09ac\u09b2\u09c7 \u0995\u09a5\u09be", "user_display": "Sayeed", "version": "2019.3.1"}, {"app_id": "io.snapcraft.pycharm-professional-Uqpw0ZWqy6Wh4mgaWE0rxgM5tAGCwf4D", "date_created": 1578237631.0, "description": "its coooollllllllllllllllllllllllllllllllllllll", "distro": "Ubuntu", "karma_down": 0, "karma_up": 0, "locale": "en_US", "rating": 100, "reported": 0, "review_id": 132951, "score": 0, "summary": "best IDE", "user_display": "ali", "version": "2019.3.1"}, {"app_id": "io.snapcraft.pycharm-professional-Uqpw0ZWqy6Wh4mgaWE0rxgM5tAGCwf4D", "date_created": 1579939695.0, "description": "Using for years and I will tell my kids to do the same.", "distro": "Ubuntu", "karma_down": 0, "karma_up": 0, "locale": "en_US", "rating": 100, "reported": 0, "review_id": 141834, "score": 0, "summary": "Just best", "user_display": "zajzajer", "version": "2019.3.2"}, {"app_id": "io.snapcraft.pycharm-professional-Uqpw0ZWqy6Wh4mgaWE0rxgM5tAGCwf4D", "date_created": 1580054883.0, "description": "pretty good software", "distro": "Ubuntu", "karma_down": 0, "karma_up": 0, "locale": "en_US", "rating": 100, "reported": 0, "review_id": 142425, "score": 0, "summary": "Loved it!", "user_display": "jafar", "version": "2019.3.2"}, {"app_id": "io.snapcraft.pycharm-professional-Uqpw0ZWqy6Wh4mgaWE0rxgM5tAGCwf4D", "date_created": 1580385195.0, "description": "very good!,I use it with python.", "distro": "Ubuntu", "karma_down": 0, "karma_up": 0, "locale": "en_US", "rating": 100, "reported": 0, "review_id": 144207, "score": 0, "summary": "good", "user_display": "garden", "version": "2019.3.2"}, {"app_id": "io.snapcraft.pycharm-professional-Uqpw0ZWqy6Wh4mgaWE0rxgM5tAGCwf4D", "date_created": 1580587769.0, "description": "It is very user friendly and has a ton of cool feature. The debugging is pretty great as well.", "distro": "Unknown", "karma_down": 0, "karma_up": 0, "locale": "en_US", "rating": 100, "reported": 0, "review_id": 145347, "score": 0, "summary": "Great app and would recommend anyone who wants to code in python", "user_display": "Sankarshana V", "version": "2019.3.2"}, {"app_id": "io.snapcraft.pycharm-professional-Uqpw0ZWqy6Wh4mgaWE0rxgM5tAGCwf4D", "date_created": 1583001904.0, "description": "Jetbrains have great products and they also have free version if you don't need all the perks.", "distro": "Ubuntu", "karma_down": 0, "karma_up": 0, "locale": "en_US", "rating": 100, "reported": 0, "review_id": 158176, "score": 0, "summary": "Deserves every dollar, euro or other currency", "user_display": "kaan", "version": "2019.3.3"}, {"app_id": "io.snapcraft.pycharm-professional-Uqpw0ZWqy6Wh4mgaWE0rxgM5tAGCwf4D", "date_created": 1583500762.0, "description": "i can't type Chinese in this IDE through Fcitx", "distro": "Ubuntu", "karma_down": 0, "karma_up": 0, "locale": "en_US", "rating": 60, "reported": 0, "review_id": 160660, "score": 0, "summary": "Great app ,but still have problem", "user_display": "No-Pepsi", "version": "2019.3.3"}, {"app_id": "io.snapcraft.pycharm-professional-Uqpw0ZWqy6Wh4mgaWE0rxgM5tAGCwf4D", "date_created": 1585561597.0, "description": "Best tool for a Python and/or Django Developer! Works great on Ubuntu!", "distro": "Ubuntu", "karma_down": 0, "karma_up": 0, "locale": "en_US", "rating": 100, "reported": 0, "review_id": 173227, "score": 0, "summary": "Best tool, works great on Ubuntu!", "user_display": "Helly", "version": "2019.3.4"}, {"app_id": "io.snapcraft.pycharm-professional-Uqpw0ZWqy6Wh4mgaWE0rxgM5tAGCwf4D", "date_created": 1586429699.0, "description": "What ever I needed, I was able to find it in this software", "distro": "Ubuntu", "karma_down": 0, "karma_up": 0, "locale": "en_US", "rating": 100, "reported": 0, "review_id": 179472, "score": 0, "summary": "Best Python IDE", "user_display": "Marko \u0106urlin", "version": "2019.3.4"}, {"app_id": "io.snapcraft.pycharm-professional-Uqpw0ZWqy6Wh4mgaWE0rxgM5tAGCwf4D", "date_created": 1587819652.0, "description": "Great understanding of Python, great git merge tools.", "distro": "Ubuntu", "karma_down": 0, "karma_up": 0, "locale": "en_US.UTF-8", "rating": 100, "reported": 0, "review_id": 191289, "score": 0, "summary": "Best Python IDE", "user_display": "Aleksey", "version": "2020.1"}, {"app_id": "io.snapcraft.pycharm-professional-Uqpw0ZWqy6Wh4mgaWE0rxgM5tAGCwf4D", "date_created": 1587893319.0, "description": "Great refactoring, inspection and general navigation functionality.", "distro": "Ubuntu", "karma_down": 0, "karma_up": 0, "locale": "en_US.UTF-8", "rating": 100, "reported": 0, "review_id": 192216, "score": 0, "summary": "Just a great tool", "user_display": "Tonni Tielens", "version": "2020.1"}, {"app_id": "io.snapcraft.pycharm-professional-Uqpw0ZWqy6Wh4mgaWE0rxgM5tAGCwf4D", "date_created": 1588009198.0, "description": "can't imagine coding without this", "distro": "Ubuntu", "karma_down": 0, "karma_up": 0, "locale": "en_IN", "rating": 100, "reported": 0, "review_id": 193755, "score": 0, "summary": "Best IDE ever", "user_display": "naveen chahar", "version": "2020.1"}, {"app_id": "io.snapcraft.pycharm-professional-Uqpw0ZWqy6Wh4mgaWE0rxgM5tAGCwf4D", "date_created": 1588481775.0, "description": "I dont't wanna talk a lot , just this is a greta IDE for python", "distro": "Ubuntu", "karma_down": 0, "karma_up": 0, "locale": "en_US.UTF-8", "rating": 100, "reported": 0, "review_id": 199227, "score": 0, "summary": "Just Great", "user_display": "mamad", "version": "2020.1"}, {"app_id": "io.snapcraft.pycharm-professional-Uqpw0ZWqy6Wh4mgaWE0rxgM5tAGCwf4D", "date_created": 1591308583.0, "description": "I does look nice though.", "distro": "Ubuntu", "karma_down": 0, "karma_up": 0, "locale": "en_US.UTF-8", "rating": 20, "reported": 0, "review_id": 224130, "score": 0, "summary": "crazy expensive", "user_display": "Brian", "version": "2020.1.2"}, {"app_id": "io.snapcraft.pycharm-professional-Uqpw0ZWqy6Wh4mgaWE0rxgM5tAGCwf4D", "date_created": 1591341320.0, "description": "I don't know exactly.", "distro": "Ubuntu", "karma_down": 0, "karma_up": 0, "locale": "en_US.UTF-8", "rating": 80, "reported": 0, "review_id": 224301, "score": 0, "summary": "Great app, but I haven't used it yet. But I know it's probably great!", "user_display": "Abror Rashid", "version": "2020.1.2"}, {"app_id": "io.snapcraft.pycharm-professional-Uqpw0ZWqy6Wh4mgaWE0rxgM5tAGCwf4D", "date_created": 1592044118.0, "description": "The best IDE for Python developers. The quality is astounding and the software is compatible with such great services like Jupyter notebook etc.", "distro": "Ubuntu", "karma_down": 0, "karma_up": 0, "locale": "en_US.UTF-8", "rating": 100, "reported": 0, "review_id": 229657, "score": 0, "summary": "Great app", "user_display": "Andrew Polukhin", "version": "2020.1.2"}, {"app_id": "io.snapcraft.pycharm-professional-Uqpw0ZWqy6Wh4mgaWE0rxgM5tAGCwf4D", "date_created": 1592549368.0, "description": "Love it! Have been using it for years!", "distro": "Ubuntu", "karma_down": 0, "karma_up": 0, "locale": "en_US.UTF-8", "rating": 100, "reported": 0, "review_id": 233494, "score": 0, "summary": "Best IDE for Python", "user_display": "Shuvo Saha", "version": "2020.1.2"}, {"app_id": "io.snapcraft.pycharm-professional-Uqpw0ZWqy6Wh4mgaWE0rxgM5tAGCwf4D", "date_created": 1593252237.0, "description": "best ide for django", "distro": "Ubuntu", "karma_down": 0, "karma_up": 0, "locale": "en_US.UTF-8", "rating": 100, "reported": 0, "review_id": 238234, "score": 0, "summary": "i love it", "user_display": "ali", "version": "2020.1.2"}, {"app_id": "io.snapcraft.pycharm-professional-Uqpw0ZWqy6Wh4mgaWE0rxgM5tAGCwf4D", "date_created": 1593510125.0, "description": "Best IDE for python and its also availabel on ubuntu software.\nThis is best firstly I have downloded vs code but pycharm has more feature than.\nIf you ask to me that what is the best IDE for python?\nmy answer will be: Pycharm Pro", "distro": "Ubuntu", "karma_down": 0, "karma_up": 0, "locale": "en_IN", "rating": 100, "reported": 0, "review_id": 239746, "score": 0, "summary": "Best IDE for python and its also availabel on ubuntu software", "user_display": "proud", "version": "2020.1.2"}, {"app_id": "io.snapcraft.pycharm-professional-Uqpw0ZWqy6Wh4mgaWE0rxgM5tAGCwf4D", "date_created": 1593909701.0, "description": "very easy and very fast.", "distro": "Ubuntu", "karma_down": 0, "karma_up": 0, "locale": "en_US.UTF-8", "rating": 100, "reported": 0, "review_id": 242272, "score": 0, "summary": "I Love This IDE MAN! It's Amazing!", "user_display": "mxlee", "version": "2020.1.2"}, {"app_id": "io.snapcraft.pycharm-professional-Uqpw0ZWqy6Wh4mgaWE0rxgM5tAGCwf4D", "date_created": 1594020894.0, "description": "why I can't find the icon in launch after I reboot?", "distro": "Ubuntu", "karma_down": 0, "karma_up": 0, "locale": "en_US", "rating": 80, "reported": 0, "review_id": 242878, "score": 0, "summary": "I can't find the icon in launch", "user_display": "Jingtao Zhang", "version": "2020.1.2"}, {"app_id": "io.snapcraft.pycharm-professional-Uqpw0ZWqy6Wh4mgaWE0rxgM5tAGCwf4D", "date_created": 1594748156.0, "description": "Its good IDE for python", "distro": "Ubuntu", "karma_down": 0, "karma_up": 0, "locale": "en_IN", "rating": 100, "reported": 0, "review_id": 247057, "score": 0, "summary": "Its good IDE for python", "user_display": "Ajay Kumar Ojha", "version": "2020.1.3"}, {"app_id": "io.snapcraft.pycharm-professional-Uqpw0ZWqy6Wh4mgaWE0rxgM5tAGCwf4D", "date_created": 1596357530.0, "description": "Globali-used...", "distro": "Ubuntu", "karma_down": 0, "karma_up": 0, "locale": "en_US.UTF-8", "rating": 100, "reported": 0, "review_id": 254457, "score": 0, "summary": "Great app I like it", "user_display": "HellmY", "version": "2020.2"}, {"app_id": "io.snapcraft.pycharm-professional-Uqpw0ZWqy6Wh4mgaWE0rxgM5tAGCwf4D", "date_created": 1597074767.0, "description": "doesnt want to start", "distro": "Ubuntu", "karma_down": 0, "karma_up": 0, "locale": "en_US.UTF-8", "rating": 20, "reported": 0, "review_id": 257494, "score": 0, "summary": "doesnt work on ubuntu 20", "user_display": "tom", "version": "2020.2"}, {"app_id": "io.snapcraft.pycharm-professional-Uqpw0ZWqy6Wh4mgaWE0rxgM5tAGCwf4D", "date_created": 1597565651.0, "description": "BEst of the best", "distro": "Ubuntu", "karma_down": 0, "karma_up": 0, "locale": "en_US.UTF-8", "rating": 100, "reported": 0, "review_id": 259470, "score": 0, "summary": "beztttttttttttt", "user_display": "Obaid ", "version": "2020.2"}, {"app_id": "io.snapcraft.pycharm-professional-Uqpw0ZWqy6Wh4mgaWE0rxgM5tAGCwf4D", "date_created": 1598241493.0, "description": "Great IDE for python, just lacks for some plugins and I am not sure whether it lacks or I am unable to find them. But overall a good IDE.", "distro": "Ubuntu", "karma_down": 0, "karma_up": 0, "locale": "en_IN", "rating": 100, "reported": 0, "review_id": 262487, "score": 0, "summary": "Good IDE for Python", "user_display": "Kuldeep", "version": "2020.2"}, {"app_id": "io.snapcraft.pycharm-professional-Uqpw0ZWqy6Wh4mgaWE0rxgM5tAGCwf4D", "date_created": 1598386679.0, "description": "This Ides is very good", "distro": "Ubuntu", "karma_down": 0, "karma_up": 0, "locale": "en_US.UTF-8", "rating": 100, "reported": 0, "review_id": 263231, "score": 0, "summary": "Super", "user_display": "namat98", "version": "2020.2"}, {"app_id": "io.snapcraft.pycharm-professional-Uqpw0ZWqy6Wh4mgaWE0rxgM5tAGCwf4D", "date_created": 1599365933.0, "description": "wasn't the whole point of snaps to compartamentalize the software? this is so dumb it's not even funny. why didn't i just download it from their website? i think it auto-updates itself either way. you ubuntu guys need to half ass more features. can't wait to see what half baked garbage you make critical part of system next.", "distro": "Ubuntu", "karma_down": 0, "karma_up": 0, "locale": "en_US.UTF-8", "rating": 40, "reported": 0, "review_id": 267901, "score": 0, "summary": "why do you snapcraft if everything unconfined?", "user_display": "alex", "version": "2020.2.1"}, {"app_id": "io.snapcraft.pycharm-professional-Uqpw0ZWqy6Wh4mgaWE0rxgM5tAGCwf4D", "date_created": 1599620300.0, "description": "Awsome software, some small teething problems but once worked out has by far best features for Jupyter Notebooks, Web Development and Machine Learning. To many features to mention here but has covered all bases. Been using Jetbrains products for many years. Real value for money if you are a serious developer. Python becomes a breeze in this environment. Great support for Git and Version Control, Database tools that are the best. Great support team to boot. ", "distro": "Ubuntu", "karma_down": 0, "karma_up": 0, "locale": "en_AU.UTF-8", "rating": 100, "reported": 0, "review_id": 269083, "score": 0, "summary": "Worth getting for Machine Learning, Advanced Python development", "user_display": "kali", "version": "2020.2.1"}, {"app_id": "io.snapcraft.pycharm-professional-Uqpw0ZWqy6Wh4mgaWE0rxgM5tAGCwf4D", "date_created": 1599678943.0, "description": "Slick, synchronized, git integration... PERFECT !", "distro": "Ubuntu", "karma_down": 0, "karma_up": 0, "locale": "en_US.UTF-8", "rating": 100, "reported": 0, "review_id": 269354, "score": 0, "summary": "Best IDE for developping Python apps", "user_display": "Arthur Pons", "version": "2020.2.1"}, {"app_id": "io.snapcraft.pycharm-professional-Uqpw0ZWqy6Wh4mgaWE0rxgM5tAGCwf4D", "date_created": 1599830772.0, "description": "A am using it from first version", "distro": "Ubuntu", "karma_down": 0, "karma_up": 0, "locale": "en_US.UTF-8", "rating": 100, "reported": 0, "review_id": 270170, "score": 0, "summary": "Simply the best dev tool", "user_display": "Gennady", "version": "2020.2.1"}, {"app_id": "io.snapcraft.pycharm-professional-Uqpw0ZWqy6Wh4mgaWE0rxgM5tAGCwf4D", "date_created": 1600334513.0, "description": "good ide python", "distro": "Ubuntu", "karma_down": 0, "karma_up": 0, "locale": "en_US.UTF-8", "rating": 100, "reported": 0, "review_id": 272438, "score": 0, "summary": "good", "user_display": "Saeid.JP", "version": "2020.2.2"}, {"app_id": "io.snapcraft.pycharm-professional-Uqpw0ZWqy6Wh4mgaWE0rxgM5tAGCwf4D", "date_created": 1600646133.0, "description": "best IDE for python ever !", "distro": "Ubuntu", "karma_down": 0, "karma_up": 0, "locale": "en_US.UTF-8", "rating": 100, "reported": 0, "review_id": 273877, "score": 0, "summary": "just wow !", "user_display": "aissam", "version": "2020.2.2"}, {"app_id": "io.snapcraft.pycharm-professional-Uqpw0ZWqy6Wh4mgaWE0rxgM5tAGCwf4D", "date_created": 1600862012.0, "description": "Recently upgraded form Pycharm CE and it was one of the best decisions I tok in my life.It's feature packed ,powerful,advanced yet easy to use, it's perfect", "distro": "Ubuntu", "karma_down": 0, "karma_up": 0, "locale": "en_IN", "rating": 100, "reported": 0, "review_id": 274785, "score": 0, "summary": "Great IDE", "user_display": "Gurkanwal Singh", "version": "2020.2.2"}, {"app_id": "io.snapcraft.pycharm-professional-Uqpw0ZWqy6Wh4mgaWE0rxgM5tAGCwf4D", "date_created": 1600951928.0, "description": "It doesn't get 5 stars because it sometimes hangs, sometimes debug mode doesn't work and some other minor bugs. But otherwise - fantastic IDE", "distro": "Ubuntu", "karma_down": 0, "karma_up": 0, "locale": "en_US", "rating": 80, "reported": 0, "review_id": 275178, "score": 0, "summary": "Mostly fantastic", "user_display": "Shani Shalgi", "version": "2020.3"}, {"app_id": "io.snapcraft.pycharm-professional-Uqpw0ZWqy6Wh4mgaWE0rxgM5tAGCwf4D", "date_created": 1602801222.0, "description": "This IDE is great, I love all this tiny helpful features and how everything works together.", "distro": "Ubuntu", "karma_down": 0, "karma_up": 0, "locale": "en_US.UTF-8", "rating": 100, "reported": 0, "review_id": 283906, "score": 0, "summary": "Awesome", "user_display": "pablo", "version": "2020.2.3"}, {"app_id": "io.snapcraft.pycharm-professional-Uqpw0ZWqy6Wh4mgaWE0rxgM5tAGCwf4D", "date_created": 1603369056.0, "description": "dfdsfsdfdsfsdfsdfsdfsdf", "distro": "Ubuntu", "karma_down": 0, "karma_up": 0, "locale": "en_IN", "rating": 100, "reported": 0, "review_id": 286397, "score": 0, "summary": "cxsdfdsfdsfsd", "user_display": "noovosoft", "version": "2020.2.3"}, {"app_id": "io.snapcraft.pycharm-professional-Uqpw0ZWqy6Wh4mgaWE0rxgM5tAGCwf4D", "date_created": 1605387866.0, "description": "best python IDE there", "distro": "Ubuntu", "karma_down": 0, "karma_up": 0, "locale": "en_US", "rating": 100, "reported": 0, "review_id": 303360, "score": 0, "summary": "best python IDE there", "user_display": "maciek", "version": "2020.2.3"}, {"app_id": "io.snapcraft.pycharm-professional-Uqpw0ZWqy6Wh4mgaWE0rxgM5tAGCwf4D", "date_created": 1605928257.0, "description": "The only downside is once you use Pycharm no other app is good enough.", "distro": "Ubuntu", "karma_down": 0, "karma_up": 0, "locale": "en_AU.UTF-8", "rating": 100, "reported": 0, "review_id": 306405, "score": 0, "summary": "Perfect for Python", "user_display": "Stephen Whitlock", "version": "2020.2.3"}, {"app_id": "io.snapcraft.pycharm-professional-Uqpw0ZWqy6Wh4mgaWE0rxgM5tAGCwf4D", "date_created": 1606243719.0, "description": "good ide for developers", "distro": "Ubuntu", "karma_down": 0, "karma_up": 0, "locale": "en_US.UTF-8", "rating": 100, "reported": 0, "review_id": 308064, "score": 0, "summary": "good", "user_display": "Talal Ahmed", "version": "2020.2.3"}, {"app_id": "io.snapcraft.pycharm-professional-Uqpw0ZWqy6Wh4mgaWE0rxgM5tAGCwf4D", "date_created": 1606409914.0, "description": "any tami people....try this ide.....best app", "distro": "Ubuntu", "karma_down": 0, "karma_up": 0, "locale": "en_IN", "rating": 100, "reported": 0, "review_id": 309024, "score": 0, "summary": "i am tamil..i recommend this", "user_display": "arun", "version": "2020.2.3"}, {"app_id": "io.snapcraft.pycharm-professional-Uqpw0ZWqy6Wh4mgaWE0rxgM5tAGCwf4D", "date_created": 1606798135.0, "description": "1. You can integrate git and make all your changes very easily.\n2. Best IDE for suggestions and auto-complete\n3. Interactive GUI for everything!\n4. Easy to configure project settings\nMany more....!", "distro": "Ubuntu", "karma_down": 0, "karma_up": 0, "locale": "en_IN", "rating": 100, "reported": 0, "review_id": 311006, "score": 0, "summary": "One app - Total set up! (I used it for python3 and it works perfectly)", "user_display": "jagadeesh", "version": "2020.2.4"}, {"app_id": "io.snapcraft.pycharm-professional-Uqpw0ZWqy6Wh4mgaWE0rxgM5tAGCwf4D", "date_created": 1606908219.0, "description": "Jupyternotebook support, web2py support (!!) and there's a whole slew of other things built in. And now with the new code-with-me it's finally adopted remote simultaneous editing, and it works like a (py)charm!", "distro": "Ubuntu", "karma_down": 0, "karma_up": 0, "locale": "en_GB.UTF-8", "rating": 100, "reported": 0, "review_id": 311502, "score": 0, "summary": "Absolutely the best python IDE i've come across", "user_display": "remco", "version": "2020.3"}, {"app_id": "io.snapcraft.pycharm-professional-Uqpw0ZWqy6Wh4mgaWE0rxgM5tAGCwf4D", "date_created": 1607519503.0, "description": "i think this is the best out of all other python IDEs", "distro": "Ubuntu", "karma_down": 0, "karma_up": 0, "locale": "en_US.UTF-8", "rating": 100, "reported": 0, "review_id": 314299, "score": 0, "summary": "very good app for professional python developers", "user_display": "Jere", "version": "2020.3"}, {"app_id": "io.snapcraft.pycharm-professional-Uqpw0ZWqy6Wh4mgaWE0rxgM5tAGCwf4D", "date_created": 1607725295.0, "description": "great one even for me as a beginner!", "distro": "Ubuntu", "karma_down": 0, "karma_up": 0, "locale": "en_PH.UTF-8", "rating": 100, "reported": 0, "review_id": 315312, "score": 0, "summary": "wondeful", "user_display": "AGZ97", "version": "2020.3"}, {"app_id": "io.snapcraft.pycharm-professional-Uqpw0ZWqy6Wh4mgaWE0rxgM5tAGCwf4D", "date_created": 1607964566.0, "description": "I use it for Web Development using Django. Works great!", "distro": "Ubuntu", "karma_down": 0, "karma_up": 0, "locale": "en_IN", "rating": 100, "reported": 0, "review_id": 316335, "score": 0, "summary": "Awesome!", "user_display": "Whiplash99", "version": "2020.3"}, {"app_id": "io.snapcraft.pycharm-professional-Uqpw0ZWqy6Wh4mgaWE0rxgM5tAGCwf4D", "date_created": 1608794825.0, "description": "suddenly stopped autocomplete for filters very annoying", "distro": "Ubuntu", "karma_down": 0, "karma_up": 0, "locale": "en_US.UTF-8", "rating": 40, "reported": 0, "review_id": 319843, "score": 0, "summary": "orm filters lookups", "user_display": "ubuntu", "version": "2020.3.1"}, {"app_id": "io.snapcraft.pycharm-professional-Uqpw0ZWqy6Wh4mgaWE0rxgM5tAGCwf4D", "date_created": 1609101888.0, "description": "really like working on it", "distro": "Ubuntu", "karma_down": 0, "karma_up": 0, "locale": "en_IL", "rating": 100, "reported": 0, "review_id": 321099, "score": 0, "summary": "the best puthon ide", "user_display": "nadeem", "version": "2020.3.1"}, {"app_id": "io.snapcraft.pycharm-professional-Uqpw0ZWqy6Wh4mgaWE0rxgM5tAGCwf4D", "date_created": 1609351014.0, "description": "Hope the support of jupyter notebook get better", "distro": "Ubuntu", "karma_down": 0, "karma_up": 0, "locale": "en_US.UTF-8", "rating": 100, "reported": 0, "review_id": 322277, "score": 0, "summary": "Great ide", "user_display": "donglai", "version": "2020.3.1"}, {"app_id": "io.snapcraft.pycharm-professional-Uqpw0ZWqy6Wh4mgaWE0rxgM5tAGCwf4D", "date_created": 1610127082.0, "description": "PyCharm's smart code editor provides first-class support for Python,", "distro": "Ubuntu", "karma_down": 0, "karma_up": 0, "locale": "en_US.UTF-8", "rating": 100, "reported": 0, "review_id": 325821, "score": 0, "summary": "Best python IDE", "user_display": "Marco Borges", "version": "2020.3.2"}, {"app_id": "io.snapcraft.pycharm-professional-Uqpw0ZWqy6Wh4mgaWE0rxgM5tAGCwf4D", "date_created": 1610214989.0, "description": "BEST PYTHON IDE EVER !!!", "distro": "Ubuntu", "karma_down": 0, "karma_up": 0, "locale": "en_CA.UTF-8", "rating": 100, "reported": 0, "review_id": 326174, "score": 0, "summary": "AWESOME!!", "user_display": "sonny", "version": "2020.3.2"}, {"app_id": "io.snapcraft.pycharm-professional-Uqpw0ZWqy6Wh4mgaWE0rxgM5tAGCwf4D", "date_created": 1611501217.0, "description": "https://www.nytimes.com/2021/01/06/us/politics/russia-cyber-hack.html", "distro": "Ubuntu", "karma_down": 0, "karma_up": 0, "locale": "en_US", "rating": 60, "reported": 0, "review_id": 332145, "score": 0, "summary": "Use any jetbrains product at your own risk", "user_display": "km445", "version": "2020.3.2"}, {"app_id": "io.snapcraft.pycharm-professional-Uqpw0ZWqy6Wh4mgaWE0rxgM5tAGCwf4D", "date_created": 1612073844.0, "description": "I've tried other IDEs for python but this one sticks out as the easiest to use with a great set of features.", "distro": "Ubuntu", "karma_down": 0, "karma_up": 0, "locale": "en_US", "rating": 100, "reported": 0, "review_id": 334892, "score": 0, "summary": "Best there is", "user_display": "Dan Brown", "version": "2020.3.3"}, {"app_id": "io.snapcraft.pycharm-professional-Uqpw0ZWqy6Wh4mgaWE0rxgM5tAGCwf4D", "date_created": 1612196850.0, "description": "How tu use Anaconda - jypiter?\n\nAnaconda for some Machine Learning sets", "distro": "Ubuntu", "karma_down": 0, "karma_up": 0, "locale": "en_US.UTF-8", "rating": 80, "reported": 0, "review_id": 335488, "score": 0, "summary": "How tu use Anaconda - jypiter?", "user_display": "jeremy2039", "version": "2020.3.3"}, {"app_id": "io.snapcraft.pycharm-professional-Uqpw0ZWqy6Wh4mgaWE0rxgM5tAGCwf4D", "date_created": 1612292700.0, "description": "A lot of features, easy to use. Best on the market", "distro": "Ubuntu", "karma_down": 0, "karma_up": 0, "locale": "en_US.UTF-8", "rating": 100, "reported": 0, "review_id": 335984, "score": 0, "summary": "Best IDE", "user_display": "jonatan", "version": "2020.3.3"}, {"app_id": "io.snapcraft.pycharm-professional-Uqpw0ZWqy6Wh4mgaWE0rxgM5tAGCwf4D", "date_created": 1612715854.0, "description": "this is only for legends who are intreseted", "distro": "Ubuntu", "karma_down": 0, "karma_up": 0, "locale": "en_IN", "rating": 100, "reported": 0, "review_id": 338045, "score": 0, "summary": "this is awsome", "user_display": "innov-dev", "version": "2020.3.3"}, {"app_id": "io.snapcraft.pycharm-professional-Uqpw0ZWqy6Wh4mgaWE0rxgM5tAGCwf4D", "date_created": 1612900879.0, "description": "There isn't a more feature rich IDE for Python than PyCharm. PyCharm has everything you want an extensive marketplace for plugins. My only complaint is that support for themes is terrible especially Jupyter notebooks. There's a ticket open for this but it gets overlooked because Jupyter has native theme support but the experience managing themes in two location sucks.", "distro": "Ubuntu", "karma_down": 0, "karma_up": 0, "locale": "en_US.UTF-8", "rating": 100, "reported": 0, "review_id": 338963, "score": 0, "summary": "PyCharm CE and Pro are the best Python IDEs", "user_display": "DaSh", "version": "2020.3.3"}, {"app_id": "io.snapcraft.pycharm-professional-Uqpw0ZWqy6Wh4mgaWE0rxgM5tAGCwf4D", "date_created": 1613239387.0, "description": "The speed of application development increases significantly. There are many convenient features for both solo and team development. I've tried a lot of IDEs, but this one beats all of them.", "distro": "Ubuntu", "karma_down": 0, "karma_up": 0, "locale": "en_US.UTF-8", "rating": 100, "reported": 0, "review_id": 340541, "score": 0, "summary": "JetBrains is undoubtedly the best IDE developer in the world", "user_display": "DeepClust", "version": "2020.3.3"}, {"app_id": "io.snapcraft.pycharm-professional-Uqpw0ZWqy6Wh4mgaWE0rxgM5tAGCwf4D", "date_created": 1613388822.0, "description": "Mostly IDEAl IDE, best on the market. A lot of useful features. Fully supports Django.", "distro": "Ubuntu", "karma_down": 0, "karma_up": 0, "locale": "en_US.UTF-8", "rating": 100, "reported": 0, "review_id": 341200, "score": 0, "summary": "Mostly IDEAl IDE, best on the market", "user_display": "metauser", "version": "2020.3.3"}, {"app_id": "io.snapcraft.pycharm-professional-Uqpw0ZWqy6Wh4mgaWE0rxgM5tAGCwf4D", "date_created": 1614223211.0, "description": "I am using pycharm since 2016 and this ide is awesome. All the features what i need in my day to day development are intergrated.", "distro": "Ubuntu", "karma_down": 0, "karma_up": 0, "locale": "en_US.UTF-8", "rating": 100, "reported": 0, "review_id": 345037, "score": 0, "summary": "Best IDE ever", "user_display": "chinthaka", "version": "2020.3.3"}, {"app_id": "io.snapcraft.pycharm-professional-Uqpw0ZWqy6Wh4mgaWE0rxgM5tAGCwf4D", "date_created": 1614459374.0, "description": "i run ubuntu on vm and pycharm really really slow", "distro": "Ubuntu", "karma_down": 0, "karma_up": 0, "locale": "en_US", "rating": 20, "reported": 0, "review_id": 346069, "score": 0, "summary": "too much ressources", "user_display": "dba", "version": "2020.3.3"}, {"app_id": "io.snapcraft.pycharm-professional-Uqpw0ZWqy6Wh4mgaWE0rxgM5tAGCwf4D", "date_created": 1614750816.0, "description": "Pycharm is literally a charm ", "distro": "Ubuntu", "karma_down": 0, "karma_up": 0, "locale": "en_US", "rating": 100, "reported": 0, "review_id": 347371, "score": 0, "summary": "Awesome IDE. Heaven for Professionals", "user_display": "NaSir", "version": "2020.3.3"}, {"app_id": "io.snapcraft.pycharm-professional-Uqpw0ZWqy6Wh4mgaWE0rxgM5tAGCwf4D", "date_created": 1615280448.0, "description": "Powerful tool to build WEB applications", "distro": "Ubuntu", "karma_down": 0, "karma_up": 0, "locale": "en_US.UTF-8", "rating": 100, "reported": 0, "review_id": 350036, "score": 0, "summary": "Awesome IDE for Python Django WEB development", "user_display": "Soyuzbek", "version": "2020.3.3"}, {"app_id": "io.snapcraft.pycharm-professional-Uqpw0ZWqy6Wh4mgaWE0rxgM5tAGCwf4D", "date_created": 1615583065.0, "description": "fuer fortnite!.", "distro": "Ubuntu", "karma_down": 0, "karma_up": 0, "locale": "en_US.UTF-8", "rating": 100, "reported": 0, "review_id": 351515, "score": 0, "summary": "fuer fortnite", "user_display": "Live session user", "version": "2020.3.3"}, {"app_id": "io.snapcraft.pycharm-professional-Uqpw0ZWqy6Wh4mgaWE0rxgM5tAGCwf4D", "date_created": 1616164347.0, "description": "its osam.love it both", "distro": "Ubuntu", "karma_down": 0, "karma_up": 0, "locale": "en_US.UTF-8", "rating": 100, "reported": 0, "review_id": 353933, "score": 0, "summary": "best app", "user_display": "Pramuditha", "version": "2020.3.4"}, {"app_id": "io.snapcraft.pycharm-professional-Uqpw0ZWqy6Wh4mgaWE0rxgM5tAGCwf4D", "date_created": 1616417630.0, "description": "You wont me needing tools like external db viewers or gitkraken anymore!", "distro": "Ubuntu", "karma_down": 0, "karma_up": 0, "locale": "en_US.UTF-8", "rating": 100, "reported": 0, "review_id": 355106, "score": 0, "summary": "Hands down the best ide", "user_display": "jonatan", "version": "2020.3.4"}, {"app_id": "io.snapcraft.pycharm-professional-Uqpw0ZWqy6Wh4mgaWE0rxgM5tAGCwf4D", "date_created": 1616938850.0, "description": "One of the best IDE !! If not the best", "distro": "Ubuntu", "karma_down": 0, "karma_up": 0, "locale": "en_US.UTF-8", "rating": 100, "reported": 0, "review_id": 357845, "score": 0, "summary": "One of the best IDE !! If not the best", "user_display": "tester", "version": "2020.3.5"}, {"app_id": "io.snapcraft.pycharm-professional-Uqpw0ZWqy6Wh4mgaWE0rxgM5tAGCwf4D", "date_created": 1619007839.0, "description": "When it works, it works very well and does exactly what it is supposed to, but it crashes on me once a week, especially when working with jupyter notebooks (which is what I do most of the time).\n\nI still like it better than all other IDEs I've tried. When only working with pure python you shouldn't encounter problems on a regular basis.\n\nIt is pretty ressource intensive, if that's an issue for you.", "distro": "Ubuntu", "karma_down": 0, "karma_up": 0, "locale": "en_US.UTF-8", "rating": 80, "reported": 0, "review_id": 367435, "score": 0, "summary": "Has problems, still the best I know", "user_display": "stephan", "version": "2021.1"}, {"app_id": "io.snapcraft.pycharm-professional-Uqpw0ZWqy6Wh4mgaWE0rxgM5tAGCwf4D", "date_created": 1668185316.0, "description": "Ich habe das Programm Installiert vermisse die m\u00f6glichkeit das Programm vorher zu testen bevor ich meine ohne hin knappe kasse belaste.\nDas programm war schnell wieder deinstalliert.\n\nSchade!!", "distro": "Ubuntu", "karma_down": 0, "karma_up": 0, "locale": "de_DE.UTF-8", "rating": 40, "reported": 0, "review_id": 537998, "score": 41, "summary": "Einsch\u00e4tzung", "user_display": "J\u00fcrgen Frenzel", "version": "2022.2.3"}, {"app_id": "io.snapcraft.pycharm-professional-Uqpw0ZWqy6Wh4mgaWE0rxgM5tAGCwf4D", "date_created": 1558422875.0, "description": "Im Grunde eine sehr gute IDE, allerdings stelle ich unter Linux immer wieder Abst\u00fcrze nach \"harmlosen\" Aktionen fest, die das Programm freezen, weil dann nur noch hart gekilled werden kann.", "distro": "Ubuntu", "karma_down": 1, "karma_up": 0, "locale": "de_DE", "rating": 60, "reported": 0, "review_id": 36157, "score": 0, "summary": "Teilweise instabil", "user_display": "Julilien", "version": "2019.1.2"}, {"app_id": "io.snapcraft.pycharm-professional-Uqpw0ZWqy6Wh4mgaWE0rxgM5tAGCwf4D", "date_created": 1564869478.0, "description": "Is the best IDE to work with python and this work with a unique performance in Ubuntu 18.04 LTS.", "distro": "Ubuntu", "karma_down": 0, "karma_up": 0, "locale": "es_CL", "rating": 100, "reported": 0, "review_id": 67831, "score": 0, "summary": "Best IDE for python", "user_display": "Jose", "version": "2019.2"}, {"app_id": "io.snapcraft.pycharm-professional-Uqpw0ZWqy6Wh4mgaWE0rxgM5tAGCwf4D", "date_created": 1572447429.0, "description": "Uno de los mejores IDEs para Python, y la instanaci\u00f3n de lo m\u00e1s sencillo que he visto en estos d\u00edas.", "distro": "Ubuntu", "karma_down": 0, "karma_up": 0, "locale": "es_PE", "rating": 100, "reported": 0, "review_id": 103548, "score": 0, "summary": "b4rt", "user_display": "b4rt", "version": "2019.2.3"}, {"app_id": "io.snapcraft.pycharm-professional-Uqpw0ZWqy6Wh4mgaWE0rxgM5tAGCwf4D", "date_created": 1588030262.0, "description": "Es un editor de codigo muy completo y r\u00e1pido.", "distro": "Ubuntu", "karma_down": 0, "karma_up": 0, "locale": "es_CO.UTF-8", "rating": 100, "reported": 0, "review_id": 194019, "score": 0, "summary": "El mejor IDE con el que he trabajado hasta el momento", "user_display": "Daniel E Rodriguez", "version": "2020.1"}, {"app_id": "io.snapcraft.pycharm-professional-Uqpw0ZWqy6Wh4mgaWE0rxgM5tAGCwf4D", "date_created": 1595982117.0, "description": "Es genial el IDE es muy practico.", "distro": "Ubuntu", "karma_down": 0, "karma_up": 0, "locale": "es_CO.UTF-8", "rating": 100, "reported": 0, "review_id": 252682, "score": 0, "summary": "Excelente", "user_display": "kike", "version": "2020.1.4"}, {"app_id": "io.snapcraft.pycharm-professional-Uqpw0ZWqy6Wh4mgaWE0rxgM5tAGCwf4D", "date_created": 1605876260.0, "description": "Una aplicacion muy caraUna aplicacion muy cara, y no compensa su precio elevado.", "distro": "Ubuntu", "karma_down": 0, "karma_up": 0, "locale": "es_ES.UTF-8", "rating": 20, "reported": 0, "review_id": 306111, "score": 0, "summary": "Una aplicacion muy cara", "user_display": "royalayn", "version": "2020.2.3"}, {"app_id": "io.snapcraft.pycharm-professional-Uqpw0ZWqy6Wh4mgaWE0rxgM5tAGCwf4D", "date_created": 1606415080.0, "description": "Sobre todo que uno puede acceder con su perfil de educaci\u00f3n.", "distro": "Ubuntu", "karma_down": 0, "karma_up": 0, "locale": "es_CL.UTF-8", "rating": 100, "reported": 0, "review_id": 309053, "score": 0, "summary": "Excelente Aplicaci\u00f3n", "user_display": "Manuel Pino", "version": "2020.2.3"}, {"app_id": "io.snapcraft.pycharm-professional-Uqpw0ZWqy6Wh4mgaWE0rxgM5tAGCwf4D", "date_created": 1613794959.0, "description": "I used it to automation tests and it have all I need. Thanks god we can acquire a licence by a uducational email", "distro": "Ubuntu", "karma_down": 0, "karma_up": 0, "locale": "es_ES.UTF-8", "rating": 100, "reported": 0, "review_id": 343099, "score": 0, "summary": "Best IDE for python", "user_display": "Carlos Botero", "version": "2020.3.3"}, {"app_id": "io.snapcraft.pycharm-professional-Uqpw0ZWqy6Wh4mgaWE0rxgM5tAGCwf4D", "date_created": 1625258558.0, "description": "El mejor IDE para desarrrollar en python", "distro": "Ubuntu", "karma_down": 0, "karma_up": 0, "locale": "es_CU", "rating": 100, "reported": 0, "review_id": 394914, "score": 0, "summary": "Excelente!!", "user_display": "D3V3L0P3RS", "version": "2021.1.3"}, {"app_id": "io.snapcraft.pycharm-professional-Uqpw0ZWqy6Wh4mgaWE0rxgM5tAGCwf4D", "date_created": 1646243674.0, "description": "el mejor entorno de desarrollo para python y sus derivados como django", "distro": "Ubuntu", "karma_down": 0, "karma_up": 0, "locale": "es_US.UTF-8", "rating": 100, "reported": 0, "review_id": 467150, "score": 0, "summary": "muy buen ide", "user_display": "Jesaias Iraola", "version": "2021.3.2"}, {"app_id": "io.snapcraft.pycharm-professional-Uqpw0ZWqy6Wh4mgaWE0rxgM5tAGCwf4D", "date_created": 1570559827.0, "description": "from today 08/october 2019 it is not working", "distro": "Ubuntu", "karma_down": 0, "karma_up": 0, "locale": "fr_FR", "rating": 20, "reported": 0, "review_id": 93744, "score": 0, "summary": "not working", "user_display": "devp1", "version": "2019.2.3"}, {"app_id": "io.snapcraft.pycharm-professional-Uqpw0ZWqy6Wh4mgaWE0rxgM5tAGCwf4D", "date_created": 1583144732.0, "description": "Toutes les applications de Jet Brains sont juste g\u00e9niales, je recommande fortement !", "distro": "Ubuntu", "karma_down": 0, "karma_up": 0, "locale": "fr_FR", "rating": 100, "reported": 0, "review_id": 158884, "score": 0, "summary": "Application juste g\u00e9niale", "user_display": "Franz", "version": "2019.3.3"}, {"app_id": "io.snapcraft.pycharm-professional-Uqpw0ZWqy6Wh4mgaWE0rxgM5tAGCwf4D", "date_created": 1595592658.0, "description": "facile d'utilisation", "distro": "Ubuntu", "karma_down": 0, "karma_up": 0, "locale": "fr_FR.UTF-8", "rating": 80, "reported": 0, "review_id": 250981, "score": 0, "summary": "super", "user_display": "Mpacko Heddy", "version": "2020.1.4"}, {"app_id": "io.snapcraft.pycharm-professional-Uqpw0ZWqy6Wh4mgaWE0rxgM5tAGCwf4D", "date_created": 1558788313.0, "description": "\u0427\u0443\u0432\u0430\u043a\u0438 \u0441\u0434\u0435\u043b\u0430\u043b\u0438 \u043a\u043b\u0430\u0441\u0441\u043d\u0443\u044e \u0448\u0442\u0443\u043a\u043e\u0432\u0438\u043d\u0443 - \u043d\u0435 \u0436\u043e\u043f\u044c\u0442\u0435\u0441\u044c, \u043a\u0443\u043f\u0438\u0442\u0435 \u043f\u043b\u0430\u0442\u043d\u0443\u044e \u043f\u043e\u0434\u043f\u0438\u0441\u043a\u0443. \u0421\u0442\u043e\u0438\u0442 \u043e\u043d\u0430 \u043a\u043e\u043f\u0435\u0439\u043a\u0438 \u043d\u0430 \u0444\u043e\u043d\u0435 \u0442\u043e\u0433\u043e \u044d\u043a\u043e\u043d\u043e\u043c\u0438\u0438 \u0432\u0440\u0435\u043c\u0435\u043d\u0438, \u043a\u043e\u0442\u043e\u0440\u044b\u0435 \u0434\u0430\u0451\u0442 PyCharm Pro.", "distro": "Ubuntu", "karma_down": 2, "karma_up": 5, "locale": "ru_RU", "rating": 100, "reported": 0, "review_id": 38138, "score": 0, "summary": "\u042d\u043a\u043e\u043d\u043e\u043c\u0438\u0442 \u0432\u0430\u0433\u043e\u043d \u0432\u0440\u0435\u043c\u0435\u043d\u0438 \u043f\u0440\u0438 \u0440\u0430\u0437\u0440\u0430\u0431\u043e\u0442\u043a\u0435", "user_display": "sf", "version": "2019.1.2"}, {"app_id": "io.snapcraft.pycharm-professional-Uqpw0ZWqy6Wh4mgaWE0rxgM5tAGCwf4D", "date_created": 1561060216.0, "description": "\u0417\u0430 \u0442\u043e \u0447\u0442\u043e \u0434\u0430\u0451\u0442\u0435 \u0432\u043e\u0437\u043c\u043e\u0436\u043d\u043e\u0441\u0442\u044c \u043f\u043e\u043b\u044c\u0437\u043e\u0432\u0430\u0442\u044c\u0441\u044f \u0432\u0430\u0448\u0435\u0439 \u043f\u0440\u043e\u0433\u0440\u0430\u043c\u043c\u043e\u0439 \u0431\u0435\u0441\u043f\u043b\u0430\u0442\u043d\u043e, \u0431\u0443\u0434\u0443\u0447\u0438 \u0441\u0442\u0443\u0434\u0435\u043d\u0442\u043e\u043c \u044d\u0442\u043e \u0437\u0434\u043e\u0440\u043e\u0432\u043e \u043f\u043e\u043c\u043e\u0433\u0430\u0435\u0442 \u043d\u0430\u0440\u0430\u0441\u0442\u0438\u0442\u044c \u0441\u043a\u0438\u043b \u0438 \u043c\u0430\u043a\u0441\u0438\u043c\u0438\u0437\u0438\u0440\u043e\u0432\u0430\u0442\u044c \u044d\u0444\u0444\u0435\u043a\u0442\u0438\u0432\u043d\u043e\u0441\u0442\u044c \u0440\u0430\u0431\u043e\u0442\u044b \u0441 \u0442\u0435\u043a\u0441\u0442\u043e\u043c. \u041a\u0430\u043a \u0432\u044b\u0443\u0447\u0443\u0441\u044c \u043e\u0431\u044f\u0437\u0430\u0442\u0435\u043b\u044c\u043d\u043e \u043a\u0443\u043f\u043b\u044e!)", "distro": "Ubuntu", "karma_down": 0, "karma_up": 0, "locale": "ru_RU", "rating": 100, "reported": 0, "review_id": 50058, "score": 0, "summary": "\u0425\u043e\u0447\u0443 \u0441\u043a\u0430\u0437\u0430\u0442\u044c \u0441\u043f\u0430\u0441\u0438\u0431\u043e Jetbrains!", "user_display": "Dovron", "version": "2019.1.3"}, {"app_id": "io.snapcraft.pycharm-professional-Uqpw0ZWqy6Wh4mgaWE0rxgM5tAGCwf4D", "date_created": 1564060570.0, "description": "\u041e\u0433\u0440\u043e\u043c\u043d\u043e\u0435 \u043a\u043e\u043b\u044c-\u0432\u043e \u0432\u043e\u0437\u043c\u043e\u0436\u043d\u043e\u0441\u0442\u0435\u0439, \u043a\u043e\u0442\u043e\u0440\u044b\u0435 \u043f\u043e\u043c\u043e\u0433\u0443\u0442 \u0432\u0430\u043c \u043d\u0430\u043f\u0438\u0441\u0430\u0442\u044c \u0432\u0430\u0448\u0435 python-\u043f\u0440\u0438\u043b\u043e\u0436\u0435\u043d\u0438\u0435 \u0432 \u0441\u0447\u0438\u0442\u0430\u043d\u044b\u0435 \u043c\u0438\u043d\u0443\u0442\u044b. \u041f\u043e \u0441\u0440\u0430\u0432\u043d\u0435\u043d\u0438\u044e \u0441 pydev \u0438\u043b\u0438 atom+plugins \u043b\u0443\u0447\u0448\u0430\u044f \u043f\u0440\u043e\u0433\u0440\u0430\u043c\u043c\u0430", "distro": "Ubuntu", "karma_down": 0, "karma_up": 0, "locale": "ru_RU", "rating": 100, "reported": 0, "review_id": 64107, "score": 0, "summary": "\u041b\u0443\u0447\u0448\u0430\u044f IDE \u0434\u043b\u044f python \u0440\u0430\u0437\u0440\u0430\u0431\u043e\u0442\u0447\u0438\u043a\u043e\u0432", "user_display": "Mark", "version": "2019.2"}, {"app_id": "io.snapcraft.pycharm-professional-Uqpw0ZWqy6Wh4mgaWE0rxgM5tAGCwf4D", "date_created": 1573789872.0, "description": "\u041e\u0442\u043b\u0438\u0447\u043d\u0430\u044f IDE. \u0423\u0434\u043e\u0431\u043d\u0430\u044f \u0432 \u0438\u0441\u043f\u043e\u043b\u044c\u0437\u043e\u0432\u0430\u043d\u0438\u0438, \u0433\u0438\u0431\u043a\u043e \u043d\u0430\u0441\u0442\u0440\u0430\u0438\u0432\u0430\u0435\u043c\u0430\u044f, \u0432\u0441\u0435 \u043d\u0435\u043e\u0431\u0445\u043e\u0434\u0438\u043c\u043e\u0435 \u0432 \u043e\u0434\u043d\u043e\u043c \u043e\u043a\u043d\u0435", "distro": "Zorin OS", "karma_down": 0, "karma_up": 0, "locale": "ru_RU", "rating": 100, "reported": 0, "review_id": 110769, "score": 0, "summary": "\u041e\u0442\u043b\u0438\u0447\u043d\u0430\u044f IDE", "user_display": "Sergey Protasov", "version": "2019.2.4"}, {"app_id": "io.snapcraft.pycharm-professional-Uqpw0ZWqy6Wh4mgaWE0rxgM5tAGCwf4D", "date_created": 1582640193.0, "description": "\u0423\u0436\u0435 \u0434\u043e\u0432\u043e\u043b\u044c\u043d\u043e \u0434\u0430\u0432\u043d\u043e \u043f\u043e\u043b\u044c\u0437\u0443\u044e\u0441\u044c, \u0432\u0441\u044f\u043a\u0438\u0439 \u0440\u0430\u0437, \u043a\u043e\u0433\u0434\u0430 \u0432\u043e\u0437\u043d\u0438\u043a\u0430\u0435\u0442 \u0432\u043e\u043f\u0440\u043e\u0441 \"\u0430 \u0432\u043e\u0442 \u044d\u0442\u043e \u0432 \u043d\u0435\u0439 \u0435\u0441\u0442\u044c?\", \u043e\u0442\u0432\u0435\u0442 \u0432\u0441\u0435\u0433\u0434\u0430 \"\u0434\u0430, \u044d\u0442\u043e \u0442\u043e\u0436\u0435 \u0435\u0441\u0442\u044c\".", "distro": "Ubuntu", "karma_down": 0, "karma_up": 0, "locale": "ru_RU", "rating": 100, "reported": 0, "review_id": 156226, "score": 0, "summary": "\u041d\u0435 IDE, \u0430 \u043a\u043e\u0441\u043c\u0438\u0447\u0435\u0441\u043a\u0438\u0439 \u043a\u043e\u0440\u0430\u0431\u043b\u044c", "user_display": "astile", "version": "2019.3.3"}, {"app_id": "io.snapcraft.pycharm-professional-Uqpw0ZWqy6Wh4mgaWE0rxgM5tAGCwf4D", "date_created": 1591532306.0, "description": "\u041a\u0430\u043a \u0447\u0435\u0440\u0435\u043f\u0430\u0445\u0430, \u0447\u0442\u043e\u0442\u043e \u0438\u043d\u0434\u0435\u043a\u0441\u0438\u0440\u0443\u0435\u0442 \u0438 \u043f\u0435\u0440\u0435\u0438\u043d\u0434\u0435\u043a\u0441\u0438\u0440\u0443\u0435\u0442.\n\u041f\u043e\u043b\u043e\u043c\u0430\u043b\u0430 \u043c\u043d\u0435 pyside2. \n\u043d\u0435\u0447\u0438\u0442\u0430\u0435\u0442 \u0438\u043c\u043f\u043e\u0440\u0442\u0438\u0440\u0443\u0435\u043c\u044b\u0435 \u0444\u0430\u0439\u043b\u044b, \u043d\u0430 windows-e \u043f\u0440\u0430\u0432\u0434\u0430. \u041d\u0430 \u0443\u0431\u0443\u043d\u0442\u0435 \u0447\u0438\u0442\u0430\u0435\u0442. \n\u0421 \u0441\u0430\u043c\u043e\u0433\u043e \u043d\u0430\u0447\u0430\u043b\u0430 \u043c\u043d\u0435 \u043d\u0435 \u043f\u043e\u043d\u0440\u0430\u0432\u0438\u043b\u0430\u0441\u044c. \u041f\u0440\u0438\u043c\u0435\u043d\u0438\u043c\u0430. \u0417\u043b\u0430 \u043d\u0430 \u043d\u0435\u0435 \u0445\u0432\u0430\u0442\u0430\u0435\u0442. \u0421\u043c\u0435\u043d\u0438\u043b \u0431\u044b \u043a \u0447\u0435\u0440\u0442\u043e\u0432\u043e\u0439 \u043c\u0430\u0442\u0435\u0440\u0438, \u0434\u0430 \u0432\u043e\u0442 \u043d\u0435\u0437\u0430\u0434\u0430\u0447\u0430, \u0443 \u0434\u0440\u0443\u0433\u0438\u0445 \u043d\u0435 \u043b\u0443\u0447\u0448\u0435.", "distro": "Ubuntu", "karma_down": 0, "karma_up": 0, "locale": "ru_RU.UTF-8", "rating": 60, "reported": 0, "review_id": 225837, "score": 0, "summary": "\u0411\u0430\u0433\u0430\u043d\u0430\u044f \u0445\u0435\u0440\u043d\u044f", "user_display": "tank", "version": "2020.1.2"}, {"app_id": "io.snapcraft.pycharm-professional-Uqpw0ZWqy6Wh4mgaWE0rxgM5tAGCwf4D", "date_created": 1594112804.0, "description": "\u041a\u0430\u043a \u0441\u0442\u0443\u0434\u0435\u043d\u0442\u0443 \u043f\u0440\u0435\u0434\u043e\u0441\u0442\u0430\u0432\u0438\u043b\u0438 \u0433\u043e\u0434 \u0431\u0435\u0441\u043f\u043b\u0430\u0442\u043d\u043e\u0433\u043e \u043f\u043e\u043b\u044c\u0437\u043e\u0432\u0430\u043d\u0438\u044f. \u042d\u043a\u043e\u043d\u043e\u043c\u0438\u0442 \u043a\u0443\u0447\u0443 \u0432\u0440\u0435\u043c\u0435\u043d\u0438 \u043f\u0440\u0438 \u0440\u0430\u0437\u0440\u0430\u0431\u043e\u0442\u043a\u0435, \u0434\u0435\u0431\u0430\u0433\u0435, \u0443\u0434\u043e\u0431\u043d\u043e \u0434\u0435\u043b\u043b\u0430\u0442\u044c \u043a\u043e\u043c\u043c\u0438\u0442\u044b, \u043d\u0435 \u043d\u0443\u0436\u043d\u043e \u043f\u043e\u0441\u0442\u043e\u044f\u043d\u043d\u043e \u043e\u0442\u043a\u0440\u044b\u0432\u0430\u0442\u044c \u043a\u043e\u043d\u0441\u043e\u043b\u044c, \u0435\u0441\u0442\u044c http \u043a\u043b\u0438\u0435\u043d\u0442 \u043f\u043e \u0442\u0438\u043f\u0443 Postman, \u043a\u043e\u0442\u043e\u0440\u044b\u0439 \u043f\u043e\u0437\u0432\u043e\u043b\u044f\u0435\u0442 \u043d\u0435 \u043e\u0442\u0445\u043e\u0434\u044f \u043e\u0442 \u043a\u0430\u0441\u0441\u044b \u043f\u0440\u043e\u0432\u0435\u0440\u044f\u0442\u044c \u044d\u043d\u0434\u043f\u043e\u0438\u043d\u0442\u044b.", "distro": "Ubuntu", "karma_down": 0, "karma_up": 0, "locale": "ru_RU", "rating": 100, "reported": 0, "review_id": 243501, "score": 0, "summary": "\u041e\u0434\u043d\u0430 \u0438\u0437 \u043b\u0443\u0447\u0448\u0438\u0445 IDE \u0434\u043b\u044f \u0440\u0430\u0437\u0440\u0430\u0431\u043e\u0442\u043a\u0438 \u043d\u0430 Python/Django", "user_display": null, "version": "2020.1.2"}, {"app_id": "io.snapcraft.pycharm-professional-Uqpw0ZWqy6Wh4mgaWE0rxgM5tAGCwf4D", "date_created": 1594222463.0, "description": "\u041f\u043e\u0436\u0430\u043b\u0443\u0439 \u043b\u0443\u0447\u0448\u0435\u0435 IDE \u0434\u043b\u044f python. \u041d\u0435\u0437\u0430\u043c\u0435\u043d\u0438\u043c\u043e \u043f\u0440\u0438 \u0440\u0430\u0431\u043e\u0442\u0435 \u0441 \u0445\u043e\u0442\u044c \u043d\u0435\u043c\u043d\u043e\u0433\u043e \u0431\u043e\u043b\u044c\u0448\u0438\u043c \u043f\u0440\u043e\u0435\u043a\u0442\u043e\u043c. \u0421\u0442\u043e\u0438\u0442 \u043a\u0430\u0436\u0434\u043e\u0433\u043e \u0437\u0430\u043f\u043b\u0430\u0447\u0435\u043d\u043d\u043e\u0433\u043e \u0440\u0443\u0431\u043b\u044f", "distro": "Ubuntu", "karma_down": 0, "karma_up": 0, "locale": "ru_RU.UTF-8", "rating": 100, "reported": 0, "review_id": 244341, "score": 0, "summary": "\u0412\u0441\u0435\u043c \u0441\u043e\u0432\u0435\u0442\u0443\u044e", "user_display": "Roman", "version": "2020.1.3"}, {"app_id": "io.snapcraft.pycharm-professional-Uqpw0ZWqy6Wh4mgaWE0rxgM5tAGCwf4D", "date_created": 1595088443.0, "description": "\u041f\u0440\u043e\u0433\u0430 \u0445\u043e\u0440\u043e\u0448\u0430\u044f, \u043f\u043b\u044e\u0441 \u0435\u0449\u0451 \u0435\u0441\u0442\u044c \u0432\u043e\u0437\u043c\u043e\u0436\u043d\u043e\u0441\u0442\u044c \u043f\u043e\u043b\u044c\u0437\u043e\u0432\u0430\u0442\u044c\u0441\u044f \u0431\u0435\u0441\u043f\u043b\u0430\u0442\u043d\u043e. \u041d\u043e \u0435\u0441\u043b\u0438 \u0443 \u0432\u0430\u0441 \u0430\u043c\u043b\u043e \u041e\u0417\u0423 \u0438\u043b\u0438 \u0432\u043e\u043e\u0431\u0449\u0435 \u0441\u043b\u0430\u0431\u044b\u0439 \u043f\u043a \u0438\u043b\u0438 \u0431\u044e\u0434\u0436\u0435\u0442\u043d\u044b\u0439 \u043d\u043e\u0443\u0442, \u0442\u043e \u044d\u0442\u043e \u043d\u0435 \u0434\u043b\u044f \u0432\u0430\u0441, \u0442.\u043a. \u0431\u0443\u0434\u0435\u0442 \u0437\u0430\u043f\u0443\u0441\u043a\u0442\u044c\u0441\u044f \u0437\u0430 2-3 \u0430 \u043c\u043e\u0436\u0435\u0442 \u0438 10 \u043c\u0438\u043d\u0443\u0442!", "distro": "Ubuntu", "karma_down": 0, "karma_up": 0, "locale": "ru_RU.UTF-8", "rating": 100, "reported": 0, "review_id": 248721, "score": 0, "summary": "\u0420\u0435\u043a\u043e\u043c\u0435\u043d\u0434\u0443\u044e! \u041d\u043e \u0435\u0441\u0442\u044c \u041d\u041e", "user_display": "Alik", "version": "2020.1.3"}, {"app_id": "io.snapcraft.pycharm-professional-Uqpw0ZWqy6Wh4mgaWE0rxgM5tAGCwf4D", "date_created": 1596390832.0, "description": "\u0446\u0443\u043a\u043a\u0446\u043a\u0446\u0446\u0446\u0446\u0446\u0446\u0446\u0446\u0446\u0446\u0446\u0446\u043a\u0446", "distro": "Ubuntu", "karma_down": 0, "karma_up": 0, "locale": "ru_RU.UTF-8", "rating": 100, "reported": 0, "review_id": 254661, "score": 0, "summary": "\u0443\u043a\u0443\u0443\u043a\u0446\u0446\u0446\u0446\u0446\u0446\u0446\u0446\u0446\u0446\u0446\u0446\u0446\u0446\u0446", "user_display": "Alex", "version": "2020.2"}, {"app_id": "io.snapcraft.pycharm-professional-Uqpw0ZWqy6Wh4mgaWE0rxgM5tAGCwf4D", "date_created": 1599491402.0, "description": "\u041e\u0447\u0435\u043d\u044c \u043a\u0440\u0443\u0442\u0430\u044f \u0441\u0440\u0435\u0434\u0430. \u041d\u0430 \u0432\u0438\u043d\u0434\u0435 \u043f\u0440\u0430\u0432\u0434\u0430 \u0434\u043e\u043b\u0433\u043e \u0437\u0430\u043f\u0443\u0441\u043a\u0430\u0435\u0442\u0441\u044f, \u043d\u043e \u043d\u0430 Ubuntu \u043e\u0442\u043b\u0438\u0447\u043d\u043e \u0440\u0430\u0431\u043e\u0442\u0430\u0435\u0442", "distro": "Ubuntu", "karma_down": 0, "karma_up": 0, "locale": "ru_RU.UTF-8", "rating": 100, "reported": 0, "review_id": 268522, "score": 0, "summary": "\u0441\u043e\u0432\u0435\u0442\u0443\u044e", "user_display": "victor", "version": "2020.2.1"}, {"app_id": "io.snapcraft.pycharm-professional-Uqpw0ZWqy6Wh4mgaWE0rxgM5tAGCwf4D", "date_created": 1612041857.0, "description": "is good but very expensive", "distro": "Ubuntu", "karma_down": 0, "karma_up": 0, "locale": "ru_RU", "rating": 60, "reported": 0, "review_id": 334792, "score": 0, "summary": "good programm", "user_display": "Dilshod", "version": "2020.3.3"}, {"app_id": "io.snapcraft.pycharm-professional-Uqpw0ZWqy6Wh4mgaWE0rxgM5tAGCwf4D", "date_created": 1628715601.0, "description": "\u0421\u043f\u0430\u0441\u0438\u0431\u043e \u0432\u0441\u0435\u043c \u043a\u0442\u043e \u043f\u0440\u0438\u043d\u0438\u043c\u0430\u043b \u0438 \u043f\u0440\u0438\u043d\u0438\u043c\u0430\u0435\u0442 \u0443\u0447\u0430\u0441\u0442\u0438\u0435 \u0432 \u0440\u0430\u0437\u0440\u0430\u0431\u043e\u0442\u043a\u0435, \u0434\u0430\u043d\u043d\u043e\u0439 IDE. \u041c\u043e\u0439 \u043b\u044e\u0431\u0438\u043c\u044b\u0439 \u0438 \u043d\u0435\u0437\u0430\u043c\u0435\u043d\u0438\u043c\u044b\u0439 \u0438\u043d\u0441\u0442\u0440\u0443\u043c\u0435\u043d\u0442.", "distro": "Ubuntu", "karma_down": 0, "karma_up": 0, "locale": "ru_RU", "rating": 100, "reported": 0, "review_id": 408446, "score": 0, "summary": "\u0440\u0435\u0441\u043f\u0435\u043a\u0442 \u043a\u043e\u043b\u043b\u0435\u0433\u0430\u043c", "user_display": "destiny", "version": "2021.2"}, {"app_id": "io.snapcraft.pycharm-professional-Uqpw0ZWqy6Wh4mgaWE0rxgM5tAGCwf4D", "date_created": 1634890982.0, "description": "Wayland support please!", "distro": "Ubuntu", "karma_down": 0, "karma_up": 0, "locale": "ru_RU.UTF-8", "rating": 80, "reported": 0, "review_id": 431306, "score": 0, "summary": "Wayland dosen't work", "user_display": "don", "version": "2021.2.3"}, {"app_id": "io.snapcraft.pycharm-professional-Uqpw0ZWqy6Wh4mgaWE0rxgM5tAGCwf4D", "date_created": 1641640194.0, "description": "\u041d\u0435 \u043f\u0440\u043e\u0431\u043e\u0432\u0430\u043b \u0434\u0440\u0443\u0433\u0438\u0435 \u043f\u0440\u043e\u0444\u0435\u0441\u0441\u0438\u043e\u043d\u0430\u043b\u044c\u043d\u044b\u0435 \u0441\u0440\u0435\u0434\u044b \u0440\u0430\u0437\u0440\u0430\u0431\u043e\u0442\u043a\u0438, \u043d\u043e \u044d\u0442\u0430 \u043c\u0435\u043d\u044f \u0432\u043f\u043e\u043b\u043d\u0435 \u0443\u0441\u0442\u0440\u0430\u0438\u0432\u0430\u0435\u0442.", "distro": "Ubuntu", "karma_down": 0, "karma_up": 0, "locale": "ru_RU", "rating": 100, "reported": 0, "review_id": 452978, "score": 0, "summary": "\u041e\u0442\u043b\u0438\u0447\u043d\u0430\u044f IDE", "user_display": "Nikolay", "version": "2021.3.1"}, {"app_id": "io.snapcraft.pycharm-professional-Uqpw0ZWqy6Wh4mgaWE0rxgM5tAGCwf4D", "date_created": 1653692351.0, "description": "\u041b\u0443\u0447\u0448\u0435\u0435 \u043f\u0440\u0438\u043b\u043e\u0436\u0435\u043d\u0438\u0435 \u0434\u043b\u044f \u043a\u043e\u0434\u0438\u043d\u0433\u0430 \u043d\u0430 python", "distro": "Ubuntu", "karma_down": 0, "karma_up": 0, "locale": "ru_RU.UTF-8", "rating": 100, "reported": 0, "review_id": 490677, "score": 0, "summary": "\u041f\u0440\u0435\u043a\u0440\u0430\u0441\u043d\u043e\u0435 \u043f\u0440\u0438\u043b\u043e\u0436\u0435\u043d\u0438\u0435", "user_display": "Yaroslav", "version": "2022.1.1"}, {"app_id": "io.snapcraft.pycharm-professional-Uqpw0ZWqy6Wh4mgaWE0rxgM5tAGCwf4D", "date_created": 1557629057.0, "description": "\u8fd8\u4e0d\u9519\uff0c\u5c31\u662f\u4e0b\u8f7d\u6709\u70b9\u6162\u8fd8\u4e0d\u9519\uff0c\u5c31\u662f\u4e0b\u8f7d\u6709\u70b9\u6162", "distro": "Ubuntu", "karma_down": 3, "karma_up": 14, "locale": "zh_CN", "rating": 100, "reported": 0, "review_id": 32399, "score": 18, "summary": "\u8fd8\u4e0d\u9519\uff0c\u5c31\u662f\u4e0b\u8f7d\u6709\u70b9\u6162", "user_display": "mayh", "version": "2019.1.2"}, {"app_id": "io.snapcraft.pycharm-professional-Uqpw0ZWqy6Wh4mgaWE0rxgM5tAGCwf4D", "date_created": 1556961626.0, "description": "\u3002\u3002\u3002\u3002\u3002\u3002\u3002\u3002\u3002\u3002\u3002\u3002\u3002\u3002\u3002\u3002\u3002\u3002\u3002", "distro": "Ubuntu", "karma_down": 8, "karma_up": 2, "locale": "zh_CN", "rating": 100, "reported": 0, "review_id": 29039, "score": 0, "summary": "good", "user_display": "aqua", "version": "2019.1.1"}, {"app_id": "io.snapcraft.pycharm-professional-Uqpw0ZWqy6Wh4mgaWE0rxgM5tAGCwf4D", "date_created": 1557906357.0, "description": "\u5728\u5bb6\u4e0b\u8f7d\u901f\u5ea6\u5012\u8fd8\u53ef\u4ee5\uff0c\u53ef\u662f\u5728\u5355\u4f4d\u2026\u2026", "distro": "Ubuntu", "karma_down": 2, "karma_up": 3, "locale": "zh_CN", "rating": 100, "reported": 0, "review_id": 33785, "score": 0, "summary": "\u901f\u5ea6\u4e0d\u662f\u6162\uff0c\u662f\u8d85\u7ea7\u6162", "user_display": "alucard", "version": "2019.1.2"}, {"app_id": "io.snapcraft.pycharm-professional-Uqpw0ZWqy6Wh4mgaWE0rxgM5tAGCwf4D", "date_created": 1560239644.0, "description": "\u8fd9\u4e2a\u662f\u4e13\u4e1a\u7248\u7684\u8f6f\u4ef6\uff0c\u9700\u8981\u6fc0\u6d3b\uff0c\u5b89\u88c5\u6bd4\u8f83\u6162\uff0c\u4f46\u529f\u80fd\u975e\u5e38\u5f3a\u5927", "distro": "Ubuntu", "karma_down": 1, "karma_up": 1, "locale": "zh_CN", "rating": 100, "reported": 0, "review_id": 45857, "score": 0, "summary": "\u5b89\u88c5\u8f83\u6162", "user_display": "yangsheng", "version": "2019.1.3"}, {"app_id": "io.snapcraft.pycharm-professional-Uqpw0ZWqy6Wh4mgaWE0rxgM5tAGCwf4D", "date_created": 1560651087.0, "description": "\u5f88\u4e0d\u9519\u7684\u8f6f\u4ef6\uff0c\u8fd9\u4e2a\u5b89\u88c5\u5b8c\u4e4b\u540e\u7684\u8def\u5f84\u5728\u90a3\u91cc,\u6211whereis pycharm\u67e5\u4e86\u4e00\u4e0b\uff0c\u597d\u51e0\u4e2a\u8def\u5f84\u5462\uff0c\u4e0d\u77e5\u9053\u54ea\u4e00\u4e2a\u624d\u662f\u771f\u6b63\u7684\u8def\u5f84", "distro": "Ubuntu", "karma_down": 0, "karma_up": 0, "locale": "zh_CN", "rating": 80, "reported": 0, "review_id": 48002, "score": 0, "summary": "\u5f88\u4e0d\u9519\u7684\u8f6f\u4ef6\uff0c\u8fd9\u4e2a\u5b89\u88c5\u5b8c\u4e4b\u540e\u7684\u8def\u5f84\u5728\u90a3\u91cc", "user_display": "flack", "version": "2019.1.3"}, {"app_id": "io.snapcraft.pycharm-professional-Uqpw0ZWqy6Wh4mgaWE0rxgM5tAGCwf4D", "date_created": 1563592956.0, "description": "\u6211\u7684\u4e0b\u8f7d\u4e0d\u4e86\u554a\u6211\u7684\u4e0b\u8f7d\u4e0d\u4e86\u554a\u6211\u7684\u4e0b\u8f7d\u4e0d\u4e86\u554a", "distro": "Ubuntu", "karma_down": 0, "karma_up": 0, "locale": "zh_CN", "rating": 60, "reported": 0, "review_id": 62166, "score": 0, "summary": "\u6211\u7684\u4e0b\u8f7d\u4e0d\u4e86\u554a", "user_display": "chopin", "version": "2019.1.3"}, {"app_id": "io.snapcraft.pycharm-professional-Uqpw0ZWqy6Wh4mgaWE0rxgM5tAGCwf4D", "date_created": 1564254858.0, "description": "\u4e0b\u8f7d\u901f\u5ea6\u8fd8\u662f\u53ef\u4ee5\u7684\uff0c\u529f\u80fd\u5f3a\u5927", "distro": "Ubuntu", "karma_down": 0, "karma_up": 0, "locale": "zh_CN", "rating": 100, "reported": 0, "review_id": 65028, "score": 0, "summary": "\u5f88\u65b9\u4fbf\uff0c\u5148\u7528\u7740", "user_display": "keyfly", "version": "2019.2"}, {"app_id": "io.snapcraft.pycharm-professional-Uqpw0ZWqy6Wh4mgaWE0rxgM5tAGCwf4D", "date_created": 1569898729.0, "description": "\u6162\u6162\u6162\u6162\u6162\u6162\u6162\u6162\u6162\u6162\u6162\u6162\u6162\u6162\u6162\u6162as", "distro": "Ubuntu", "karma_down": 0, "karma_up": 0, "locale": "zh_CN", "rating": 100, "reported": 0, "review_id": 90714, "score": 0, "summary": "\u6162\u6162\u6162\u6162", "user_display": "xy", "version": "2019.2.3"}, {"app_id": "io.snapcraft.pycharm-professional-Uqpw0ZWqy6Wh4mgaWE0rxgM5tAGCwf4D", "date_created": 1570785193.0, "description": "\u5b89\u88c5\u76ee\u5f55\u5728 /snap/xxx", "distro": "Ubuntu", "karma_down": 0, "karma_up": 0, "locale": "zh_CN", "rating": 100, "reported": 0, "review_id": 94737, "score": 0, "summary": "\u63a8\u8350\u4f7f\u7528", "user_display": "an", "version": "2019.2.3"}, {"app_id": "io.snapcraft.pycharm-professional-Uqpw0ZWqy6Wh4mgaWE0rxgM5tAGCwf4D", "date_created": 1575791815.0, "description": "\u901f\u5ea6\u53ef\u4ee5\u3002\u3002\u3002\u3002\u3002\u3002\u3002\u3002\u3002\u3002\u3002\u3002", "distro": "Ubuntu", "karma_down": 0, "karma_up": 0, "locale": "zh_CN", "rating": 100, "reported": 0, "review_id": 120903, "score": 0, "summary": "\u901f\u5ea6\u8fd8\u4e0d\u9519", "user_display": "Liao Chen", "version": "2019.3"}, {"app_id": "io.snapcraft.pycharm-professional-Uqpw0ZWqy6Wh4mgaWE0rxgM5tAGCwf4D", "date_created": 1580379672.0, "description": "\u5b89\u88c5\u4e0d\u4e86\u554a", "distro": "Ubuntu", "karma_down": 0, "karma_up": 0, "locale": "zh_CN", "rating": 100, "reported": 0, "review_id": 144168, "score": 0, "summary": "\u65e0\u6cd5\u5b89\u88c5", "user_display": "wwu", "version": "2019.3.2"}, {"app_id": "io.snapcraft.pycharm-professional-Uqpw0ZWqy6Wh4mgaWE0rxgM5tAGCwf4D", "date_created": 1582723097.0, "description": "\u7ad9\u70b9\u662f\u5728\u6708\u7403\u4f20\u9001\u6570\u636e\u5417\uff1f\u4e0b\u4e2a\u5341\u51e0\u5206\u949f\u624d1%\uff0c\u5176\u4ed6\u8f6f\u4ef6\u90fd\u5b89\u88c5\u5b8c\u6bd5\u4e86\uff0c\u8fd9\u4e2a\u8fd8\u5728\u9f9f\u901f\u4e0b\u8f7d", "distro": "Ubuntu", "karma_down": 0, "karma_up": 0, "locale": "zh_CN", "rating": 20, "reported": 0, "review_id": 156703, "score": 0, "summary": "\u4e0b\u8f7d\u901f\u5ea6\u592a\u6162", "user_display": "kylin", "version": "2019.3.3"}, {"app_id": "io.snapcraft.pycharm-professional-Uqpw0ZWqy6Wh4mgaWE0rxgM5tAGCwf4D", "date_created": 1583143044.0, "description": "\u56fd\u5185\u7684\u786e\u662f\u5f88\u6162,\u56e0\u4e3a\u9632\u706b\u5899\u7684\u539f\u56e0\u5427,\u5b98\u7f51\u4e0b\u8f7d\u4e5f\u662f\u5f88\u6162", "distro": "Ubuntu", "karma_down": 0, "karma_up": 0, "locale": "zh_CN", "rating": 100, "reported": 0, "review_id": 158863, "score": 0, "summary": "\u5f88\u4e0d\u9519\u7684Python\u4e13\u7528IDE,\u6211\u5728\u56fd\u5916,\u5b89\u88c5\u5f88\u5feb,", "user_display": "Xander", "version": "2019.3.3"}, {"app_id": "io.snapcraft.pycharm-professional-Uqpw0ZWqy6Wh4mgaWE0rxgM5tAGCwf4D", "date_created": 1583419087.0, "description": "\u4e0b\u8f7d\u6162\u53ef\u4ee5\u66f4\u6362\u4e3a\u56fd\u5185\u6e90\uff0c\uff0c \u65b9\u6cd5\u81ea\u5df1\u767e\u5ea6", "distro": "Ubuntu", "karma_down": 0, "karma_up": 0, "locale": "zh_CN", "rating": 100, "reported": 0, "review_id": 160270, "score": 0, "summary": "\u4e0b\u8f7d\u6162\u53ef\u4ee5\u66f4\u6362\u4e3a\u56fd\u5185\u6e90", "user_display": "wangbo", "version": "2019.3.3"}, {"app_id": "io.snapcraft.pycharm-professional-Uqpw0ZWqy6Wh4mgaWE0rxgM5tAGCwf4D", "date_created": 1586672609.0, "description": "\u4fee\u6539\u914d\u7f6e\u540e\u542f\u52a8\u4e0d\u4e86\uff0c\u91cd\u88c5\u8f6f\u4ef6\u65e0\u6cd5\u89e3\u51b3\u3002", "distro": "Ubuntu", "karma_down": 0, "karma_up": 0, "locale": "zh_CN", "rating": 100, "reported": 0, "review_id": 181329, "score": 0, "summary": "\u5982\u4f55\u5f7b\u5e95\u5378\u8f7d", "user_display": "Langkye", "version": "2020.1"}, {"app_id": "io.snapcraft.pycharm-professional-Uqpw0ZWqy6Wh4mgaWE0rxgM5tAGCwf4D", "date_created": 1591004614.0, "description": "\u4e0b\u8f7d\u6bd4Jetbrains Toolbox\u6162\u591a\u4e86\uff0c\u4e0d\u8fc7Toolbox\u6709\u70b9\u95ee\u9898\uff0c\u8fd8\u662f\u51d1\u5408\u7528\u8fd9\u4e2a\u5427", "distro": "Ubuntu", "karma_down": 0, "karma_up": 0, "locale": "zh_CN.UTF-8", "rating": 80, "reported": 0, "review_id": 221649, "score": 0, "summary": "\u4e0b\u8f7d\u8f83\u6162", "user_display": "Mitchell", "version": "2020.1.1"}, {"app_id": "io.snapcraft.pycharm-professional-Uqpw0ZWqy6Wh4mgaWE0rxgM5tAGCwf4D", "date_created": 1592111243.0, "description": "\u6bcf\u6b21\u5b89\u88c5\u90fd\u662f\u5361\u5728\u767e\u5206\u4e4b\u5341\uff0c\u7136\u540e\u663e\u793a\u4e0d\u80fd\u5b89\u88c5", "distro": "Ubuntu", "karma_down": 0, "karma_up": 0, "locale": "zh_CN.UTF-8", "rating": 100, "reported": 0, "review_id": 230248, "score": 0, "summary": "\u95ee\u4e00\u4e0b\u5927\u5bb6\u4e3a\u4ec0\u4e48\u5b89\u88c5\u4e0d\u4e86\uff1f", "user_display": "ubuntu20.04", "version": "2020.1.2"}, {"app_id": "io.snapcraft.pycharm-professional-Uqpw0ZWqy6Wh4mgaWE0rxgM5tAGCwf4D", "date_created": 1593390787.0, "description": "hao aaaaaaaaaaaaaaaaaaaaaaaaaaaaa", "distro": "Ubuntu", "karma_down": 0, "karma_up": 0, "locale": "zh_CN.UTF-8", "rating": 100, "reported": 0, "review_id": 239071, "score": 0, "summary": "haoaaaaaaaa", "user_display": "Linux", "version": "2020.1.2"}, {"app_id": "io.snapcraft.pycharm-professional-Uqpw0ZWqy6Wh4mgaWE0rxgM5tAGCwf4D", "date_created": 1595252435.0, "description": "!!!!!!!!!!!", "distro": "Ubuntu", "karma_down": 0, "karma_up": 0, "locale": "zh_CN.UTF-8", "rating": 100, "reported": 0, "review_id": 249480, "score": 0, "summary": "goooooooood", "user_display": "Charlotte", "version": "2020.1.3"}, {"app_id": "io.snapcraft.pycharm-professional-Uqpw0ZWqy6Wh4mgaWE0rxgM5tAGCwf4D", "date_created": 1596358246.0, "description": "\u5e94\u7528\u662f\u597d\u5e94\u7528 \u5c31\u662f\u4e0b\u8f7d\u6162\u6162\u6162\u6162\u6162\u6162\u6162\u6162", "distro": "Ubuntu", "karma_down": 0, "karma_up": 0, "locale": "zh_CN.UTF-8", "rating": 100, "reported": 0, "review_id": 254460, "score": 0, "summary": "\u6162\u6162\u6162\u6162\u6162", "user_display": "yangyi", "version": "2020.2"}, {"app_id": "io.snapcraft.pycharm-professional-Uqpw0ZWqy6Wh4mgaWE0rxgM5tAGCwf4D", "date_created": 1596705580.0, "description": "\u65e0\u6cd5\u8f93\u5165\u4e2d\u6587\u3002\u3002\u3002\u3002\u3002\u3002\u3002\u3002\u3002\u3002\u3002\u3002\u3002\u3002\u3002\u3002\u3002", "distro": "Ubuntu", "karma_down": 0, "karma_up": 0, "locale": "zh_CN.UTF-8", "rating": 80, "reported": 0, "review_id": 255900, "score": 0, "summary": "\u65e0\u6cd5\u8f93\u5165\u4e2d\u6587", "user_display": "hxw", "version": "2020.2"}, {"app_id": "io.snapcraft.pycharm-professional-Uqpw0ZWqy6Wh4mgaWE0rxgM5tAGCwf4D", "date_created": 1603511556.0, "description": "\u5f88\u68d2\u7684\u5e94\u7528\uff0c\u5f88\u6162\u7684\u4e0b\u8f7d\u3002\u6709\u6ca1\u6709\u5927\u795e\u8bc4\u8bba\u533a\u8bf4\u4e0b\u548b\u529e\uff1f", "distro": "Ubuntu", "karma_down": 0, "karma_up": 0, "locale": "zh_CN", "rating": 100, "reported": 0, "review_id": 287310, "score": 0, "summary": "\u5f88\u68d2\u7684\u5e94\u7528\uff0c\u5f88\u6162\u7684\u4e0b\u8f7d\u3002\u6709\u6ca1\u6709\u5927\u795e\u8bc4\u8bba\u533a\u8bf4\u4e0b\u548b\u529e\uff1f", "user_display": "zhang", "version": "2020.2.3"}, {"app_id": "io.snapcraft.pycharm-professional-Uqpw0ZWqy6Wh4mgaWE0rxgM5tAGCwf4D", "date_created": 1603885876.0, "description": "668888888888888888888888", "distro": "Ubuntu", "karma_down": 0, "karma_up": 0, "locale": "zh_CN", "rating": 60, "reported": 0, "review_id": 291147, "score": 0, "summary": "\u4e0e\u641c\u72d7\u8f93\u5165\u6cd5\u4e0d\u517c\u5bb9\uff0c\u6709\u6ca1\u6709\u89e3\u51b3\u7684\u65b9\u6848", "user_display": "adcwb", "version": "2020.2.3"}, {"app_id": "io.snapcraft.pycharm-professional-Uqpw0ZWqy6Wh4mgaWE0rxgM5tAGCwf4D", "date_created": 1608263298.0, "description": "\u5b89\u88c5\u76f8\u6bd4\u8f83\u5176\u4ed6deb\u5305\u8981\u6162\u4e9b\uff0c\u9700\u8981\u6fc0\u6d3b\u7801\uff0c\u4f46\u7528\u7740\u771f\u9999\u3002", "distro": "Ubuntu", "karma_down": 0, "karma_up": 0, "locale": "zh_CN.UTF-8", "rating": 100, "reported": 0, "review_id": 317719, "score": 0, "summary": "\u529f\u80fd\u542c\u5f3a\u5927\uff0c\u7528\u7684\u633a\u9999", "user_display": "EastChinaTiger", "version": "2020.3"}, {"app_id": "io.snapcraft.pycharm-professional-Uqpw0ZWqy6Wh4mgaWE0rxgM5tAGCwf4D", "date_created": 1609514313.0, "description": "\u5730OOOOOOOOOOOOOOOOOOOOOOOOOOOOOOOK", "distro": "Ubuntu", "karma_down": 0, "karma_up": 0, "locale": "zh_CN.UTF-8", "rating": 100, "reported": 0, "review_id": 322956, "score": 0, "summary": "\u597dOOOOOOOOOOOOOOOK", "user_display": "haocheng", "version": "2020.3.2"}, {"app_id": "io.snapcraft.pycharm-professional-Uqpw0ZWqy6Wh4mgaWE0rxgM5tAGCwf4D", "date_created": 1610536810.0, "description": "\u6ca1\u53d1\u4e0b\u8f7d  \u603b\u6570\u63d0\u793a\u65e0\u6cd5\u5b89\u88c5", "distro": "Ubuntu", "karma_down": 0, "karma_up": 0, "locale": "zh_CN", "rating": 40, "reported": 0, "review_id": 327744, "score": 0, "summary": "\u6ca1\u53d1\u4e0b\u8f7d  \u603b\u6570\u63d0\u793a\u65e0\u6cd5\u5b89\u88c5", "user_display": "toor", "version": "2020.3.2"}, {"app_id": "io.snapcraft.pycharm-professional-Uqpw0ZWqy6Wh4mgaWE0rxgM5tAGCwf4D", "date_created": 1611800052.0, "description": "\uff01\uff01\uff01\uff01\uff01\uff01\uff01\uff01\uff01\uff01\uff01\uff01111", "distro": "Ubuntu", "karma_down": 0, "karma_up": 0, "locale": "zh_CN.UTF-8", "rating": 100, "reported": 0, "review_id": 333654, "score": 0, "summary": "\u63a8\u8350\u4f7f\u7528\uff0c\u975e\u5e38\u597d\u53cb \u00b7\u00b7\u00b7\u00b7\u00b7\u00b7\u00b7\u00b7\u00b7\u00b7\u00b7\u00b7\u00b7\u00b7\u00b7\u00b7\u00b7\u00b7\u00b7\u00b7\u00b7\u00b7\u00b7\u00b7\u00b7\u00b7\u00b7\u00b7\u00b7\u00b7\u00b7\u00b7\u00b7\u00b7\u00b7\u00b7\u00b7\u00b7\u00b7\u00b7\u00b7\u00b7\u00b7\u00b7\u00b7\u00b7\u00b7\u00b7", "user_display": "xuxiaojian", "version": "2020.3.3"}, {"app_id": "io.snapcraft.pycharm-professional-Uqpw0ZWqy6Wh4mgaWE0rxgM5tAGCwf4D", "date_created": 1630981668.0, "description": "\u65b9\u4fbf\u597d\u7528 \u6700\u5f3aide\n\u65e0\u8111\u63a8\u8350", "distro": "Ubuntu", "karma_down": 0, "karma_up": 0, "locale": "zh_CN.UTF-8", "rating": 100, "reported": 0, "review_id": 417545, "score": 0, "summary": "\u5f88\u4e0d\u9519", "user_display": "zephyrus", "version": "2021.2.1"}, {"app_id": "io.snapcraft.pycharm-professional-Uqpw0ZWqy6Wh4mgaWE0rxgM5tAGCwf4D", "date_created": 1631682435.0, "description": "\u4e13\u4e1a\u7248\u6709\u5b66\u751f\u4f18\u60e0\uff0c\u826f\u5fc3\u5230\u4f4d\uff0c\u6211\u7528\u8fc7\u7684\u6700\u597d\u7528\u7684IDE", "distro": "Ubuntu", "karma_down": 0, "karma_up": 0, "locale": "zh_CN.UTF-8", "rating": 100, "reported": 0, "review_id": 420048, "score": 0, "summary": "\u5f88\u5f3a\u7684IDE\uff0c\u63a8\u8350\u4f7f\u7528", "user_display": "togekel", "version": "2021.2.1"}]