[{"app_id": "pingus.desktop", "date_created": 1548811382.0, "description": "A really fun and nice game!", "distro": "Ubuntu", "karma_down": 0, "karma_up": 1, "locale": "en_US", "rating": 100, "reported": 0, "review_id": 14488, "score": 0, "summary": "Nice game!", "user_display": "Hassan", "version": "0.7.6-4build2"}, {"app_id": "pingus.desktop", "date_created": 1560512956.0, "description": "give this game a try it really fun to play you have to save the penguins to try to get them home.", "distro": "Ubuntu", "karma_down": 0, "karma_up": 0, "locale": "en_US", "rating": 100, "reported": 0, "review_id": 47300, "score": 0, "summary": "love this game its fun and very relaxing game", "user_display": "Irishrose", "version": "0.7.6"}, {"app_id": "pingus.desktop", "date_created": 1561578482.0, "description": "it is very lovely game to use brain. hope developer could upgrade more levels in it", "distro": "Ubuntu", "karma_down": 0, "karma_up": 0, "locale": "en_IN", "rating": 100, "reported": 0, "review_id": 52545, "score": 0, "summary": "i loved this game", "user_display": "RAHUL DEV", "version": "0.7.6"}, {"app_id": "pingus.desktop", "date_created": 1570714404.0, "description": "niet leuk oqkzkd oqkdpokqopkds", "distro": "Ubuntu", "karma_down": 0, "karma_up": 0, "locale": "en_US", "rating": 20, "reported": 0, "review_id": 94410, "score": 0, "summary": "pokke saai", "user_display": "Alessio", "version": "0.7.6"}, {"app_id": "pingus.desktop", "date_created": 1585346441.0, "description": "Fun to play, cool !", "distro": "Debian GNU/Linux", "karma_down": 0, "karma_up": 0, "locale": "en_US", "rating": 100, "reported": 0, "review_id": 171790, "score": 0, "summary": "Very nice", "user_display": "onur", "version": "0.7.6"}, {"app_id": "pingus.desktop", "date_created": 1587668659.0, "description": "I've tried my hand at a few Linux games, and I find this one the most entertaining and fun. I highly recommend you give this one a try!", "distro": "Ubuntu", "karma_down": 0, "karma_up": 0, "locale": "en_US", "rating": 100, "reported": 0, "review_id": 189408, "score": 0, "summary": "Best Linux game so far", "user_display": "Scott Little", "version": "0.7.6-5.1"}, {"app_id": "pingus.desktop", "date_created": 1589071577.0, "description": "Literally the stupid penguin walks so slow i can't even", "distro": "Ubuntu", "karma_down": 0, "karma_up": 0, "locale": "en_US", "rating": 40, "reported": 0, "review_id": 205125, "score": 0, "summary": "This game sucks", "user_display": "Neema", "version": "0.7.6"}, {"app_id": "pingus.desktop", "date_created": 1595258346.0, "description": "it works smoothly and it is not pixelated", "distro": "Ubuntu", "karma_down": 0, "karma_up": 0, "locale": "en_US", "rating": 100, "reported": 0, "review_id": 249505, "score": 0, "summary": "awesome app", "user_display": "the awesome dude", "version": "0.7.6"}, {"app_id": "pingus.desktop", "date_created": 1601159115.0, "description": "It's in the name", "distro": "Ubuntu", "karma_down": 0, "karma_up": 0, "locale": "en_US.UTF-8", "rating": 100, "reported": 0, "review_id": 276145, "score": 0, "summary": "PINGAS!", "user_display": "Emerson", "version": "0.7.6"}, {"app_id": "pingus.desktop", "date_created": 1611139474.0, "description": "Pingus is poggers", "distro": "Ubuntu", "karma_down": 0, "karma_up": 0, "locale": "en_US.UTF-8", "rating": 100, "reported": 0, "review_id": 330378, "score": 0, "summary": "Great Game", "user_display": "Kenny", "version": "0.7.6"}, {"app_id": "pingus.desktop", "date_created": 1612569123.0, "description": "Did you know it's a myth that lemmings walk off cliffs?", "distro": "Ubuntu", "karma_down": 0, "karma_up": 0, "locale": "en_US.UTF-8", "rating": 20, "reported": 0, "review_id": 337345, "score": 0, "summary": "I think I know why lemmings stopped being famous.", "user_display": "Happy Tribal", "version": "0.7.6"}, {"app_id": "pingus.desktop", "date_created": 1612647054.0, "description": "Warning keep a glass of water at your side at all times to avoid severe headaches!", "distro": "Ubuntu", "karma_down": 0, "karma_up": 0, "locale": "en_US.UTF-8", "rating": 20, "reported": 0, "review_id": 337706, "score": 0, "summary": "Good if you want a headache", "user_display": "Blu", "version": "0.7.6"}, {"app_id": "pingus.desktop", "date_created": 1615314897.0, "description": "Good Graphisc and physics BUT, not playable.\nI loved the original and played all the way thru, the levelsets are not winnable and you can't advance, the Story mode is too simple.", "distro": "Ubuntu", "karma_down": 0, "karma_up": 0, "locale": "en_US.UTF-8", "rating": 40, "reported": 0, "review_id": 350221, "score": 0, "summary": "Unplayable version of Lemmings", "user_display": "jed", "version": "0.7.6"}, {"app_id": "pingus.desktop", "date_created": 1619640643.0, "description": "Oops, I accidentally ate all of my pingus", "distro": "Ubuntu", "karma_down": 0, "karma_up": 0, "locale": "en_US.UTF-8", "rating": 100, "reported": 0, "review_id": 370510, "score": 0, "summary": "\"I ate all my pingus\"", "user_display": "Corvaex Centauri", "version": "0.7.6"}, {"app_id": "pingus.desktop", "date_created": 1619914824.0, "description": "since i downloaded it like a week ago and then i deleted it (i didn't like the game very much), and since that week my pc does some weird things from time to time, look my ubtnu 18.04.5 LTS have a ram memory of 7.6 GB processor is intel core i5 2.50 * 8\ni also have downloaded super tux kart (it's basically the best game in this weird place until now) and super tux, maybe the maleware came from those?\nbut no, I feel that the maleware is more probable to come from this game, not the others\nand yes of course i had downloaded some software other than games like wine, dolphin and citra emulator, but my pc was fine then, it didn't start to act weird but since I downloaded this game even still happens after I deleted it", "distro": "Ubuntu", "karma_down": 0, "karma_up": 0, "locale": "en_US", "rating": 40, "reported": 0, "review_id": 371815, "score": 0, "summary": "guys is this game infected with maleware?", "user_display": "ahmed", "version": "0.7.6"}, {"app_id": "pingus.desktop", "date_created": 1623416841.0, "description": "...............", "distro": "Ubuntu", "karma_down": 0, "karma_up": 0, "locale": "en_GB.UTF-8", "rating": 100, "reported": 0, "review_id": 387640, "score": 0, "summary": "Nice puzzle game", "user_display": "gaming", "version": "0.7.6"}, {"app_id": "pingus.desktop", "date_created": 1626529491.0, "description": "PINGUS from youtube poops", "distro": "Zorin OS", "karma_down": 0, "karma_up": 0, "locale": "en_CA", "rating": 100, "reported": 0, "review_id": 400045, "score": 0, "summary": "ytp", "user_display": "Daniel Aaron Hampson", "version": "0.7.6"}, {"app_id": "pingus.desktop", "date_created": 1637767664.0, "description": "This is the only game in linux I played most and I really like it. so nice puzzels and so much fun.", "distro": "Ubuntu", "karma_down": 0, "karma_up": 0, "locale": "en_IN", "rating": 100, "reported": 0, "review_id": 441110, "score": 0, "summary": "The best", "user_display": "RAHUL DEV", "version": "0.7.6"}, {"app_id": "pingus.desktop", "date_created": 1639824350.0, "description": "i really love this game! and that you can create your own levels is super cool!!", "distro": "Ubuntu", "karma_down": 0, "karma_up": 0, "locale": "en_US.UTF-8", "rating": 100, "reported": 0, "review_id": 447926, "score": 0, "summary": "Geat game! i recommend to play it!", "user_display": "Auktumas", "version": "0.7.7"}, {"app_id": "pingus.desktop", "date_created": 1648918986.0, "description": "But cool", "distro": "Ubuntu", "karma_down": 0, "karma_up": 0, "locale": "en_US.UTF-8", "rating": 60, "reported": 0, "review_id": 475131, "score": 0, "summary": "Not that fun....", "user_display": "Frank", "version": "0.7.6"}, {"app_id": "pingus.desktop", "date_created": 1661186988.0, "description": "pingus\n10/10. Hope this game isnt completely abandoned.", "distro": "Linux Mint", "karma_down": 0, "karma_up": 0, "locale": "en_US", "rating": 100, "reported": 0, "review_id": 511852, "score": 0, "summary": "haha", "user_display": "Jsneed", "version": "0.7.6-5.1"}, {"app_id": "pingus.desktop", "date_created": 1667745859.0, "description": "My first memories of gamer rage were playing this game.", "distro": "Ubuntu", "karma_down": 0, "karma_up": 0, "locale": "en_GB.UTF-8", "rating": 80, "reported": 0, "review_id": 536482, "score": 0, "summary": "the memories..", "user_display": "Ben", "version": "0.7.6"}, {"app_id": "pingus.desktop", "date_created": 1676441763.0, "description": "Its a great game but not when it crashes like a million times which is usual. It's obviously NOT malware cause everything in the Ubuntu repo is open source but it's really badly made. You can't really blame it though, since it hasn't been updated in a decade and two years.", "distro": "Ubuntu", "karma_down": 0, "karma_up": 0, "locale": "en_AU", "rating": 60, "reported": 0, "review_id": 564318, "score": 0, "summary": "Crashes like a Self-driving tesla", "user_display": "Max Parry", "version": "0.7.6"}, {"app_id": "pingus.desktop", "date_created": 1691718808.0, "description": "i cant belive how amazing well this game was built. Best Game Yet!", "distro": "Ubuntu", "karma_down": 0, "karma_up": 0, "locale": "en_US", "rating": 100, "reported": 0, "review_id": 598700, "score": 0, "summary": "Amazing", "user_display": "Tunawuna", "version": "0.7.6-5.1"}, {"app_id": "pingus.desktop", "date_created": 1709113752.0, "description": "Really Interesting and fun to play. It makes thinking a fun", "distro": "Debian GNU/Linux", "karma_down": 0, "karma_up": 0, "locale": "en_IN", "rating": 100, "reported": 0, "review_id": 615838, "score": 0, "summary": "Loved the game", "user_display": "Kausikan R", "version": "0.7.6"}, {"app_id": "org.seul.pingus", "date_created": 1608428592.0, "description": "Great game but music not working...\n[ERROR /run/build/pingus/src/engine/sound/sound_real.cpp:113] Can't load music: /app/share/pingus/music/pingus-1.it' -- skipping\n Mix_Error: Unrecognized music format", "distro": "Linux Mint", "karma_down": 0, "karma_up": 0, "locale": "en_GB.UTF-8", "rating": 60, "reported": 0, "review_id": 318381, "score": 0, "summary": "Great game but music not working", "user_display": "Jason Hill", "version": "stable"}, {"app_id": "org.seul.pingus", "date_created": 1653079838.0, "description": "Playing this again is nostalgic but it's still as infuriating as 7 yo me found it.", "distro": "Ubuntu", "karma_down": 0, "karma_up": 0, "locale": "en_GB.UTF-8", "rating": 80, "reported": 0, "review_id": 488628, "score": 0, "summary": "Nostalgic", "user_display": "Ben", "version": "0.7.6"}, {"app_id": "org.seul.pingus", "date_created": 1677890152.0, "description": "Crashes on my machine. Seems like a fun game though.", "distro": "Fedora Linux", "karma_down": 0, "karma_up": 0, "locale": "en_US", "rating": 40, "reported": 0, "review_id": 569706, "score": 0, "summary": "F37", "user_display": "Fedora", "version": "0.7.6-543-g25d7f3ffb"}, {"app_id": "org.seul.pingus", "date_created": 1713075457.0, "description": "gv67t g67m\n\n\nAhmed", "distro": "Fedora", "karma_down": 0, "karma_up": 0, "locale": "en_GB.UTF-8", "rating": 100, "reported": 0, "review_id": 619860, "score": 0, "summary": "jjj", "user_display": "\u062d\u0645\u062f \u0641\u0647\u062f", "version": "stable"}, {"app_id": "pingus.desktop", "date_created": 1558019536.0, "description": "voll lustigvoll lustigvoll lustigvoll lustig", "distro": "Ubuntu", "karma_down": 0, "karma_up": 0, "locale": "de_DE", "rating": 100, "reported": 0, "review_id": 34403, "score": 0, "summary": "voll lustig", "user_display": "andi", "version": "0.7.6"}, {"app_id": "pingus.desktop", "date_created": 1567943170.0, "description": "Ich finde es wirklich spannend und herausfordernd, aber eben auch l\u00f6sbar. je \u00f6fter ich es spiele, so mehr Feinheiten entdecke ich noch. Zum einen die Entscheidung dar\u00fcber, welche Pingus zum Einsatz kommen und zudem, sie zum pr\u00e4zisen Zeit einzusetzen. Manchmal ist es sehr einfach, doch dann auch sehr kniffelig und es braucht etliche Versuche um die L\u00f6sung zu finden und dann auch umzusetzen!\nsehr empfehlenswert!", "distro": "Ubuntu", "karma_down": 0, "karma_up": 0, "locale": "de_DE", "rating": 100, "reported": 0, "review_id": 81682, "score": 0, "summary": "Begeisterung - sehr empfehlenswert!", "user_display": "Ursula Honerlage", "version": "0.7.6"}, {"app_id": "pingus.desktop", "date_created": 1586893627.0, "description": "Sch\u00f6ne Grafik und gut gemachte Einleitung ! Sehr Sch\u00f6n .", "distro": "Ubuntu", "karma_down": 0, "karma_up": 0, "locale": "de_DE", "rating": 100, "reported": 0, "review_id": 183213, "score": 0, "summary": "Gut gemacht", "user_display": "Hans-Peter", "version": "0.7.6"}, {"app_id": "pingus.desktop", "date_created": 1606770272.0, "description": "Ein wunderbares Spiel. Sch\u00f6\u00f6\u00f6\u00f6n old school.", "distro": "Ubuntu", "karma_down": 0, "karma_up": 0, "locale": "de_DE.UTF-8", "rating": 100, "reported": 0, "review_id": 310877, "score": 0, "summary": "Retro par excellence", "user_display": "Christoph Bu\u00df", "version": "0.7.6"}, {"app_id": "pingus.desktop", "date_created": 1677172974.0, "description": "Grafik: naja - Musik: nervig - Vollbild: Verarsche, da das Spielfeld in Briefmarkengr\u00f6\u00dfe bleibt und man stattdessen einen riesigigen schwarzen Rahmen kriegt.", "distro": "KDE neon", "karma_down": 0, "karma_up": 0, "locale": "de_DE", "rating": 20, "reported": 0, "review_id": 567123, "score": 0, "summary": "Schrott", "user_display": "Vau Haa", "version": "0.7.6-5.1"}, {"app_id": "pingus.desktop", "date_created": 1677172974.0, "description": "Grafik: naja - Musik: nervig - Vollbild: Verarsche, da das Spielfeld in Briefmarkengr\u00f6\u00dfe bleibt und man stattdessen einen riesigigen schwarzen Rahmen kriegt.", "distro": "KDE neon", "karma_down": 0, "karma_up": 0, "locale": "de_DE", "rating": 20, "reported": 0, "review_id": 567126, "score": 0, "summary": "Schrott", "user_display": "Vau Haa", "version": "0.7.6-5.1"}, {"app_id": "pingus.desktop", "date_created": 1557768889.0, "description": "puedes pasar horas de diversi\u00f3n. procura terminar tu trabajo antes de empezar a jugarlo", "distro": "Ubuntu", "karma_down": 0, "karma_up": 1, "locale": "es_ES", "rating": 100, "reported": 0, "review_id": 33125, "score": 0, "summary": "un deleite", "user_display": "ezeziel basilio", "version": "0.7.6"}, {"app_id": "pingus.desktop", "date_created": 1558391706.0, "description": "hace a\u00f1os que no juego esta obra maestra llega 2019 y finalmente horas y horas de diversion", "distro": "Ubuntu", "karma_down": 0, "karma_up": 0, "locale": "es_VE", "rating": 100, "reported": 0, "review_id": 36022, "score": 0, "summary": "jajaja amo este juego", "user_display": "maxi", "version": "0.7.6"}, {"app_id": "pingus.desktop", "date_created": 1569277418.0, "description": "Me la apso chevere con el juego", "distro": "Ubuntu", "karma_down": 0, "karma_up": 0, "locale": "es_MX", "rating": 100, "reported": 0, "review_id": 87873, "score": 0, "summary": "divertidisimo bueno PARA MI", "user_display": "Edenilzon", "version": "0.7.6"}, {"app_id": "pingus.desktop", "date_created": 1579495670.0, "description": "El juego esta bastante logrado. Los gr\u00e1ficos est\u00e1n buenos, si bien no es un juego con muchos efectos, cumple su funci\u00f3n, entretiene y ademas consume muy poco recursos, cualquier computadora por mas b\u00e1sica que sea puede correr el juego.", "distro": "Ubuntu", "karma_down": 0, "karma_up": 0, "locale": "es_AR", "rating": 100, "reported": 0, "review_id": 139380, "score": 0, "summary": "Muy buen juego!", "user_display": "Ricardo", "version": "0.7.6"}, {"app_id": "pingus.desktop", "date_created": 1588091706.0, "description": "se usa mucho la estrategia y de como usar a los pinguins", "distro": "Ubuntu", "karma_down": 0, "karma_up": 0, "locale": "es_MX", "rating": 100, "reported": 0, "review_id": 194691, "score": 0, "summary": "es el mejor juego", "user_display": "Galindo", "version": "0.7.6"}, {"app_id": "pingus.desktop", "date_created": 1594297165.0, "description": "La probare... a ver como va, mi ni\u00f1o, la termino y le encanto...", "distro": "Ubuntu", "karma_down": 0, "karma_up": 0, "locale": "es_DO.UTF-8", "rating": 80, "reported": 0, "review_id": 244887, "score": 0, "summary": "A mi ni\u00f1o le encanto..", "user_display": "Rodolfo Urena", "version": "0.7.6"}, {"app_id": "pingus.desktop", "date_created": 1603303112.0, "description": "mi discord es: OAEM77#5929", "distro": "Ubuntu", "karma_down": 0, "karma_up": 0, "locale": "es_UY", "rating": 100, "reported": 0, "review_id": 286108, "score": 0, "summary": "discord", "user_display": "OAEM", "version": "0.7.6"}, {"app_id": "pingus.desktop", "date_created": 1622597455.0, "description": "espro este juego", "distro": "Ubuntu", "karma_down": 0, "karma_up": 0, "locale": "es_ES.UTF-8", "rating": 80, "reported": 0, "review_id": 384303, "score": 0, "summary": "saul", "user_display": "goku", "version": "0.7.6"}, {"app_id": "pingus.desktop", "date_created": 1623836180.0, "description": "Jebe arpueba este juego", "distro": "Ubuntu", "karma_down": 0, "karma_up": 0, "locale": "es_ES", "rating": 100, "reported": 0, "review_id": 389235, "score": 0, "summary": "No es privativo como Lemming", "user_display": "Pax", "version": "0.7.6"}, {"app_id": "pingus.desktop", "date_created": 1627430813.0, "description": "es un juego muy divertido y muy entretenido", "distro": "Ubuntu", "karma_down": 0, "karma_up": 0, "locale": "es_ES.UTF-8", "rating": 100, "reported": 0, "review_id": 403490, "score": 0, "summary": "es muy genial", "user_display": "ceibal", "version": "0.7.6"}, {"app_id": "pingus.desktop", "date_created": 1629925634.0, "description": "es hermosa me encantan los pinguinos en este caso los pingus", "distro": "Ubuntu", "karma_down": 0, "karma_up": 0, "locale": "es_VE", "rating": 100, "reported": 0, "review_id": 413306, "score": 0, "summary": "la recomiendo", "user_display": "kotoko neko", "version": "0.7.6"}, {"app_id": "pingus.desktop", "date_created": 1630531796.0, "description": "buena fvbgbggggggggggggggggggggg", "distro": "Ubuntu", "karma_down": 0, "karma_up": 0, "locale": "es_PE.UTF-8", "rating": 100, "reported": 0, "review_id": 415869, "score": 0, "summary": "la recomiendo rftgtttioiop", "user_display": "\u00c1lvaro", "version": "0.7.6"}, {"app_id": "pingus.desktop", "date_created": 1630541335.0, "description": "no quiero ser malo pero es algo malo", "distro": "Ubuntu", "karma_down": 0, "karma_up": 0, "locale": "es_ES.UTF-8", "rating": 20, "reported": 0, "review_id": 415907, "score": 0, "summary": "me gusta", "user_display": "ceibal", "version": "0.7.6"}, {"app_id": "pingus.desktop", "date_created": 1632611561.0, "description": "No me gusta, la quiero desinstalar yyyyyyyyyyyyyyyyyyyyyyyyyyyyyyyyyyyyyyyyyyyyyyyyyyyyyyyyyy NO SE DESINSTALA.\nGGGGGGGGGGGGGGGGGGGGGGGGRRRRRRRRRRRRRRRRRRRRRRRRRRRRRRRRRRRRRRRRRRRRRRRRRRRRRRRRRRRRRRRRRRRRRRRRRRRRRRRRRRRRRRRRRRRRRRRRRRRRRRRRRRRRRRRRRRRRRRRRRRRRRRRRRRRRRRRRRRRRRRRRRRRRRRRRRRR.", "distro": "Ubuntu", "karma_down": 0, "karma_up": 0, "locale": "es_AR", "rating": 20, "reported": 0, "review_id": 423602, "score": 0, "summary": "LA DETESTO", "user_display": "qui", "version": "0.7.6"}, {"app_id": "pingus.desktop", "date_created": 1639055716.0, "description": "aaaaaaaaaaaaaaaaaaaaaaaaaaaaaaaaaaaaaaaaaaaaaaaaaaaaaaaaaaaaaaaaaaaaaaaaaaaaaaaaaaaaaaaaaaaaaaaaaaaaaaaaaaaaaaaaaaaaaaaaaaaaaaaaaaaaaaaaaaaaaaaaaaaaaaaaaaaaaaaaaaaaaaaaaaaaaaaaaaaaaaaaae", "distro": "Ubuntu", "karma_down": 0, "karma_up": 0, "locale": "es_ES.UTF-8", "rating": 80, "reported": 0, "review_id": 445487, "score": 0, "summary": "recomieno", "user_display": "Fran", "version": "0.7.6"}, {"app_id": "pingus.desktop", "date_created": 1648062872.0, "description": "me gusta qua ndo es otros niveles", "distro": "Ubuntu", "karma_down": 0, "karma_up": 0, "locale": "es_AR.UTF-8", "rating": 100, "reported": 0, "review_id": 472400, "score": 0, "summary": "me encanta", "user_display": "ClaudioCastro", "version": "0.7.6"}, {"app_id": "pingus.desktop", "date_created": 1665340313.0, "description": "Me encanta, puedo estar horas sin parar de jugarlo. Lo recomiendo, pero siempre ponte un l\u00edmite de tiempo por que si no pueden pasar muchas horas sin que te des cuenta.", "distro": "Ubuntu", "karma_down": 0, "karma_up": 0, "locale": "es_ES", "rating": 100, "reported": 0, "review_id": 527143, "score": 0, "summary": "Muy divertido", "user_display": "peques", "version": "0.7.6"}, {"app_id": "pingus.desktop", "date_created": 1711278545.0, "description": "For some reason, this game does not work at full screen for me.", "distro": "Debian GNU/Linux", "karma_down": 0, "karma_up": 0, "locale": "es_ES", "rating": 60, "reported": 0, "review_id": 618143, "score": 0, "summary": "Not working at fullscreen", "user_display": "Mega Man", "version": "0.7.6-5.1"}, {"app_id": "org.seul.pingus", "date_created": 1647651493.0, "description": "Sufro retraso mental y diarrea cr\u00f3nica, y este juego me cur\u00f3 ambas cosas.\n\nGracias, Pingus.", "distro": "KDE neon", "karma_down": 0, "karma_up": 0, "locale": "es_UY", "rating": 100, "reported": 0, "review_id": 471200, "score": 0, "summary": "Juegardo!", "user_display": "Netwalker", "version": "0.7.6-543-g25d7f3ffb (stable)"}, {"app_id": "org.seul.pingus", "date_created": 1675506413.0, "description": "En la pantalla 10 se queda colgado y hay que cerrarlo y no se puede continuar.", "distro": "Fedora Linux", "karma_down": 0, "karma_up": 0, "locale": "es_ES.UTF-8", "rating": 40, "reported": 0, "review_id": 561303, "score": 0, "summary": "Se queda colgado", "user_display": "chorny", "version": "0.7.6"}, {"app_id": "pingus.desktop", "date_created": 1567626063.0, "description": "Rien n'a \u00e9t\u00e9 propos\u00e9 depuis 2012", "distro": "Ubuntu", "karma_down": 0, "karma_up": 0, "locale": "fr_FR", "rating": 60, "reported": 0, "review_id": 80278, "score": 0, "summary": "A quand une MAJ digne de ce sigle?", "user_display": "Arnaud Garoux", "version": "0.7.6"}, {"app_id": "pingus.desktop", "date_created": 1581083215.0, "description": "Gregory dis que c'est nul a chier", "distro": "Ubuntu", "karma_down": 0, "karma_up": 0, "locale": "fr_FR", "rating": 100, "reported": 0, "review_id": 147991, "score": 0, "summary": "cool", "user_display": "Louis", "version": "0.7.6"}, {"app_id": "pingus.desktop", "date_created": 1588199834.0, "description": "Super clone de lemmings. J'ai fais les 5 ou 6 sc\u00e9narios avec chacuns une dizaine de niveaux. Tr\u00e8s bon mix entre casse t\u00eate et arcade.", "distro": "Ubuntu", "karma_down": 0, "karma_up": 0, "locale": "fr_FR", "rating": 100, "reported": 0, "review_id": 196017, "score": 0, "summary": "Tr\u00e8s bien", "user_display": "Simon", "version": "0.7.6"}, {"app_id": "pingus.desktop", "date_created": 1588201646.0, "description": "C'est super mignon, je recommande cette appli.", "distro": "Ubuntu", "karma_down": 0, "karma_up": 0, "locale": "fr_FR", "rating": 100, "reported": 0, "review_id": 196056, "score": 0, "summary": "Tr\u00e8s bon casse t\u00eate Lemmings", "user_display": "silverGreg", "version": "0.7.6"}, {"app_id": "pingus.desktop", "date_created": 1660470993.0, "description": "Jeu plut\u00f4t bien au d\u00e9but, sur \"l'\u00eele des apprentissages\". Les niveaux ne sont pas trop durs, mais pas super faciles non plus. \nMais une fois pass\u00e9, \u00e7a devient compliqu\u00e9. Dans les \"autres niveaux\", je suis bloqu\u00e9e sur tous les th\u00e8mes, et la plupart je n'ai m\u00eame pas r\u00e9ussi le premier niveau.", "distro": "Ubuntu", "karma_down": 0, "karma_up": 0, "locale": "fr_FR.UTF-8", "rating": 60, "reported": 0, "review_id": 509720, "score": 0, "summary": "Je recommande pour ceux qui aiment bien les casse-t\u00eates", "user_display": "Mimi", "version": "0.7.6"}, {"app_id": "pingus.desktop", "date_created": 1532757632.0, "description": "Simple point and click", "distro": "Debian GNU/Linux", "karma_down": 0, "karma_up": 0, "locale": "ru_RU", "rating": 100, "reported": 0, "review_id": 8685, "score": 0, "summary": "Old school!", "user_display": "nikobit", "version": "0.7.6"}]