[{"app_id": "sgt-loopy.desktop", "date_created": 1625035756.0, "description": "cacacacacaca no me gusta es muy feo", "distro": "Ubuntu", "karma_down": 0, "karma_up": 0, "locale": "es_ES.UTF-8", "rating": 20, "reported": 0, "review_id": 394002, "score": 0, "summary": "caca", "user_display": "ceibal", "version": "20191231.79a5378"}, {"app_id": "sgt-loopy.desktop", "date_created": 1665405750.0, "description": "One of the best of the collection, but others games are great too", "distro": "Ubuntu", "karma_down": 0, "karma_up": 0, "locale": "fr_FR.UTF-8", "rating": 100, "reported": 0, "review_id": 527369, "score": 33, "summary": "Great puzzles !", "user_display": "wpodlejski", "version": "20191231.79a5378"}, {"app_id": "sgt-loopy.desktop", "date_created": 1644834760.0, "description": "Several nice grids (not just the square one), different levels of difficulty and the possibility to personalize each game.", "distro": "Ubuntu", "karma_down": 0, "karma_up": 0, "locale": "fr_CA.UTF-8", "rating": 100, "reported": 0, "review_id": 463124, "score": 0, "summary": "My favorite game!", "user_display": "carole", "version": "20191231.79a5378"}]