[{"app_id": "weatherintheclock_JasonLG1979.github.io", "date_created": 1557139569.0, "description": "No working in Ubuntu 19.04", "distro": "Ubuntu", "karma_down": 0, "karma_up": 7, "locale": "en_IN", "rating": 20, "reported": 0, "review_id": 29942, "score": 14, "summary": "Not working", "user_display": "Gopal", "version": "unknown"}, {"app_id": "weatherintheclock_JasonLG1979.github.io", "date_created": 1522836126.0, "description": "showing exactly what needed, you can open weather via click in menu", "distro": "Red Hat Enterprise Linux Workstation", "karma_down": 4, "karma_up": 25, "locale": "en_US", "rating": 100, "reported": 0, "review_id": 7066, "score": 0, "summary": "very brief piece of info", "user_display": "vbenes", "version": "unknown"}, {"app_id": "weatherintheclock_JasonLG1979.github.io", "date_created": 1525984679.0, "description": "I can't find any changes with this extension. Doesn't give error notification in Tweaks, either.", "distro": "Fedora", "karma_down": 0, "karma_up": 7, "locale": "en_US", "rating": 20, "reported": 0, "review_id": 7650, "score": 0, "summary": "Doesn't seem to do anything for me in F28...?", "user_display": "aatu", "version": "unknown"}, {"app_id": "weatherintheclock_JasonLG1979.github.io", "date_created": 1526913247.0, "description": "Local weather right on your desktop.", "distro": "Fedora", "karma_down": 0, "karma_up": 1, "locale": "en_US", "rating": 100, "reported": 0, "review_id": 7815, "score": 0, "summary": "Simple, and does the job", "user_display": "Minna", "version": "unknown"}, {"app_id": "weatherintheclock_JasonLG1979.github.io", "date_created": 1529354180.0, "description": "is not working any more!", "distro": "Kali GNU/Linux", "karma_down": 0, "karma_up": 2, "locale": "en_CA", "rating": 20, "reported": 0, "review_id": 8193, "score": 0, "summary": "not working", "user_display": null, "version": "unknown"}, {"app_id": "weatherintheclock_JasonLG1979.github.io", "date_created": 1536938948.0, "description": "Shows the weather in the clock. Working fine in Fedora 28.", "distro": "Fedora", "karma_down": 1, "karma_up": 1, "locale": "en_US", "rating": 100, "reported": 0, "review_id": 9348, "score": 0, "summary": "Great", "user_display": "Robert Bergin", "version": "unknown"}, {"app_id": "weatherintheclock_JasonLG1979.github.io", "date_created": 1549050202.0, "description": "does just whats needed", "distro": "Arch Linux", "karma_down": 0, "karma_up": 0, "locale": "en_US", "rating": 100, "reported": 0, "review_id": 14659, "score": 0, "summary": "nice", "user_display": null, "version": "unknown"}, {"app_id": "weatherintheclock_JasonLG1979.github.io", "date_created": 1556296729.0, "description": "For proper and complete working of this extension you need gnome weather", "distro": "Ubuntu", "karma_down": 1, "karma_up": 1, "locale": "en_IN", "rating": 80, "reported": 0, "review_id": 25772, "score": 0, "summary": "Does not active when internet connection is disconnected", "user_display": "Adnan Dar", "version": "unknown"}, {"app_id": "weatherintheclock_JasonLG1979.github.io", "date_created": 1556345748.0, "description": "Installed Gnome weather, logged out & in, installed gnome-shell-extention- weather... \"Works for me!\"", "distro": "Ubuntu", "karma_down": 0, "karma_up": 3, "locale": "en_US", "rating": 100, "reported": 0, "review_id": 26021, "score": 0, "summary": "Works in Bionic Beaver", "user_display": "Jose Esparza", "version": "unknown"}, {"app_id": "weatherintheclock_JasonLG1979.github.io", "date_created": 1559251016.0, "description": "Other extentions work well except of this", "distro": "Ubuntu", "karma_down": 0, "karma_up": 0, "locale": "en_US", "rating": 40, "reported": 0, "review_id": 40652, "score": 0, "summary": "Doesnt work on 18", "user_display": "N7", "version": "unknown"}, {"app_id": "weatherintheclock_JasonLG1979.github.io", "date_created": 1559827939.0, "description": "no things apeared in kali linux 2019", "distro": "Kali GNU/Linux", "karma_down": 0, "karma_up": 0, "locale": "en_US", "rating": 20, "reported": 0, "review_id": 43862, "score": 0, "summary": "no thing", "user_display": null, "version": "unknown"}, {"app_id": "weatherintheclock_JasonLG1979.github.io", "date_created": 1561965904.0, "description": "Not working on latest kali", "distro": "Kali GNU/Linux", "karma_down": 0, "karma_up": 0, "locale": "en_IN", "rating": 20, "reported": 0, "review_id": 54360, "score": 0, "summary": "Not working!", "user_display": null, "version": "unknown"}, {"app_id": "weatherintheclock_JasonLG1979.github.io", "date_created": 1566930444.0, "description": "workd perfectly in ubuntu 19.04 with gnome-weather installed. just installed and it worked.", "distro": "Ubuntu", "karma_down": 0, "karma_up": 0, "locale": "en_US", "rating": 100, "reported": 0, "review_id": 77140, "score": 0, "summary": "works like a charm", "user_display": "flooijdt", "version": "unknown"}, {"app_id": "weatherintheclock_JasonLG1979.github.io", "date_created": 1576923400.0, "description": "Does Not Work in Fresh Fedora Workstation 21 Installation", "distro": "Fedora", "karma_down": 0, "karma_up": 0, "locale": "en_US", "rating": 20, "reported": 0, "review_id": 126543, "score": 0, "summary": "Does Not Work in Fresh Fedora Workstation 21 Installation", "user_display": "Sebastian Reuter", "version": "unknown"}, {"app_id": "weatherintheclock_JasonLG1979.github.io", "date_created": 1581125600.0, "description": "It doesn't work on Ubuntu 19.10, even I log out & in. It still doesn't work.", "distro": "Ubuntu", "karma_down": 0, "karma_up": 0, "locale": "en_US", "rating": 40, "reported": 0, "review_id": 148213, "score": 0, "summary": "wouldn't recommend in Ubuntu 19.10", "user_display": "Stephen", "version": "unknown"}, {"app_id": "weatherintheclock_JasonLG1979.github.io", "date_created": 1588571696.0, "description": "Not working for me in 18.04. I have GNOME Weather installed and also restarted the computer.", "distro": "Ubuntu", "karma_down": 0, "karma_up": 0, "locale": "en_US", "rating": 40, "reported": 0, "review_id": 200166, "score": 0, "summary": "Not working", "user_display": "Nino", "version": "unknown"}, {"app_id": "weatherintheclock_JasonLG1979.github.io", "date_created": 1608692907.0, "description": "Works for me no problem.", "distro": "postmarketOS", "karma_down": 0, "karma_up": 0, "locale": "C", "rating": 100, "reported": 0, "review_id": 319474, "score": 0, "summary": "Working on PostmarketOS PineTab", "user_display": "Joseph Walker", "version": "unknown"}, {"app_id": "weatherintheclock_JasonLG1979.github.io", "date_created": 1583754762.0, "description": "Zeigt das Wetter in Deutschland nicht an. Vereinigte Staaten zbs. funktioniert...", "distro": "Ubuntu", "karma_down": 0, "karma_up": 0, "locale": "de_DE", "rating": 40, "reported": 0, "review_id": 161986, "score": 0, "summary": "..", "user_display": "Eddie", "version": "unknown"}, {"app_id": "weatherintheclock_JasonLG1979.github.io", "date_created": 1559684442.0, "description": "could not display app on dock", "distro": "Ubuntu", "karma_down": 0, "karma_up": 1, "locale": "es_ES", "rating": 20, "reported": 0, "review_id": 43064, "score": 0, "summary": "does NOT Work", "user_display": "Manuel", "version": "unknown"}, {"app_id": "weatherintheclock_JasonLG1979.github.io", "date_created": 1540630882.0, "description": "\u041d\u0435\u0442 \u0437\u0430\u044f\u0432\u043b\u0435\u043d\u044b\u0445 \u0444\u0443\u043d\u043a\u0446\u0438\u0439, \u043d\u0430\u0441\u0442\u0440\u043e\u0435\u043a \u0442\u043e\u0436\u0435 \u043d\u0435\u0442", "distro": "Kali GNU/Linux", "karma_down": 0, "karma_up": 0, "locale": "ru_RU", "rating": 20, "reported": 0, "review_id": 10002, "score": 0, "summary": "\u041d\u0435 \u0440\u0430\u0431\u043e\u0442\u0430\u0435\u0442", "user_display": null, "version": "unknown"}, {"app_id": "weatherintheclock_JasonLG1979.github.io", "date_created": 1572101081.0, "description": "No work ubunto 18", "distro": "Ubuntu", "karma_down": 0, "karma_up": 0, "locale": "ru_RU", "rating": 20, "reported": 0, "review_id": 101649, "score": 0, "summary": "No work ubunto 18", "user_display": "Ami", "version": "unknown"}]