[{"app_id": "zenmap-root.desktop", "date_created": 1547954777.0, "description": "Tried using UMIT but not as user friendly as Zenmap.", "distro": "Fedora", "karma_down": 1, "karma_up": 1, "locale": "en_GB", "rating": 100, "reported": 0, "review_id": 13942, "score": 0, "summary": "Awesome as CLI GUIS's go", "user_display": "administrator", "version": "7.70-1"}, {"app_id": "zenmap-root.desktop", "date_created": 1600925606.0, "description": "YOU WILL BE SECURED IF U INSTALL AND USE IT : D", "distro": "Debian GNU/Linux", "karma_down": 0, "karma_up": 0, "locale": "en_US", "rating": 100, "reported": 0, "review_id": 275083, "score": 0, "summary": "good software", "user_display": "RedBull4", "version": "7.70"}]